{"listings":[{"unitSummaries":{"reserved":null,"general":[{"unitType":"2 BR","totalUnits":1,"priorities":null,"minSquareFt":780,"minRentalMinIncome":6990.0,"minPercentIncome":null,"minOccupancy":2,"minMonthlyRent":3495.0,"maxSquareFt":780,"maxRentalMinIncome":6990.0,"maxPercentIncome":null,"maxOccupancy":5,"maxMonthlyRent":3495.0,"listingID":"a0W0P00000F84RuUAJ"}]},"reservedDescriptor":null,"prioritiesDescriptor":null,"listingID":"a0W0P00000F84RuUAJ","Name":"1400 Mission Unit 1500","Units_Available":1,"Building_Name":"1400 Mission","Building_Street_Address":"1400 Mission","Building_City":"San Francisco","Building_State":"CA","Building_Zip_Code":"94103","LastModifiedDate":"2018-02-28T00:15:03.000+0000","Application_Due_Date":"2018-05-01T22:42:00.000+0000","Building_URL":"http://sfmohcd.org/sites/default/files/Documents/MOH/Housing%20Listing%20Photos/1400%20Mission.jpg","Lottery_Results_Date":"2018-02-28","Lottery_Date":"2018-02-27T20:00:00.000+0000","Lottery_Results":false,"Accepting_Online_Applications":true,"Building_Selection_Criteria":"http://sfmohcd.org/sites/default/files/Resident%20Selection%20Criteria/1400-Mission-Building-Selection-Criteria-1.19.2018.pdf","Reserved_community_minimum_age":65,"Reserved_community_type":"Senior","hasWaitlist":false,"Id":"a0W0P00000F84RuUAJ","imageURL":"http://sfmohcd.org/sites/default/files/Documents/MOH/Housing%20Listing%20Photos/1400%20Mission.jpg"},{"unitSummaries":{"reserved":null,"general":[{"unitType":"2 BR","totalUnits":1,"priorities":null,"minSquareFt":846,"minRentalMinIncome":2596.0,"minPercentIncome":null,"minOccupancy":2,"minMonthlyRent":1298.0,"maxSquareFt":846,"maxRentalMinIncome":2596.0,"maxPercentIncome":null,"maxOccupancy":5,"maxMonthlyRent":1298.0,"listingID":"a0W0P00000F8bl9UAB"}]},"reservedDescriptor":null,"prioritiesDescriptor":null,"listingID":"a0W0P00000F8bl9UAB","Name":"Potrero Launch Unit  W305","Units_Available":1,"Building_Name":"Potrero Launch","Building_Street_Address":"2235 Third Street","Building_City":"San Francisco","Building_State":"CA","Building_Zip_Code":"94107","LastModifiedDate":"2018-02-28T00:30:32.000+0000","Application_Due_Date":"2018-03-06T01:00:00.000+0000","Building_URL":"http://sfmohcd.org/sites/default/files/Documents/MOH/Housing%20Listing%20Photos/PotreroLaunch.jpg","Lottery_Results_Date":"2018-03-23","Lottery_Date":"2018-03-22T18:30:00.000+0000","Lottery_Results":false,"Accepting_Online_Applications":true,"Building_Selection_Criteria":"http://sfmohcd.org/sites/default/files/Resident%20Selection%20Criteria/RQA%20-%20Affordable%20-%20San%20Francisco%20Sites%201-20-17.pdf","Reserved_community_minimum_age":0,"hasWaitlist":false,"Id":"a0W0P00000F8bl9UAB","imageURL":"http://sfmohcd.org/sites/default/files/Documents/MOH/Housing%20Listing%20Photos/PotreroLaunch.jpg"},{"unitSummaries":{"reserved":null,"general":[{"unitType":"Studio","totalUnits":1,"priorities":null,"minSquareFt":209,"minRentalMinIncome":3025.0,"minPercentIncome":null,"minOccupancy":1,"minMonthlyRent":1210.0,"maxSquareFt":209,"maxRentalMinIncome":3025.0,"maxPercentIncome":null,"maxOccupancy":2,"maxMonthlyRent":1210.0,"listingID":"a0W0P00000F8PoNUAV"}]},"reservedDescriptor":null,"prioritiesDescriptor":null,"listingID":"a0W0P00000F8PoNUAV","Name":"77 Bluxome Unit 110","Units_Available":1,"Building_Name":"77 Bluxome","Building_Street_Address":"77 Bluxome Street","Building_City":"San Francisco","Building_State":"CA","Building_Zip_Code":"94107","LastModifiedDate":"2018-02-27T01:11:41.000+0000","Application_Due_Date":"2018-02-21T01:00:00.000+0000","Building_URL":"https://i.imgur.com/Jh8OHJY.jpg","Lottery_Results_Date":"2018-03-08","Lottery_Date":"2018-03-07T21:31:00.000+0000","Lottery_Results":false,"Accepting_Online_Applications":true,"Building_Selection_Criteria":"http://sfmohcd.org/sites/default/files/Resident%20Selection%20Criteria/Equity%20Rental%20Criteria%202-12-18.pdf","Reserved_community_minimum_age":0,"hasWaitlist":false,"Id":"a0W0P00000F8PoNUAV","imageURL":"https://i.imgur.com/Jh8OHJY.jpg"},{"unitSummaries":{"reserved":null,"general":[{"unitType":"Studio","totalUnits":1,"priorities":null,"minSquareFt":587,"minRentalMinIncome":5500.0,"minPercentIncome":null,"minOccupancy":1,"minMonthlyRent":2200.0,"maxSquareFt":587,"maxRentalMinIncome":5500.0,"maxPercentIncome":null,"maxOccupancy":2,"maxMonthlyRent":2200.0,"listingID":"a0W0P00000F8EVwUAN"}]},"reservedDescriptor":null,"prioritiesDescriptor":null,"listingID":"a0W0P00000F8EVwUAN","Name":"Ava 55 Ninth Unit 314","Units_Available":1,"Building_Name":"AVA 55 Ninth","Building_Street_Address":"55 9th Street","Building_City":"San Francisco","Building_State":"CA","Building_Zip_Code":"94103","LastModifiedDate":"2018-02-24T05:58:51.000+0000","Application_Due_Date":"2018-02-16T01:00:00.000+0000","Building_URL":"http://sfmohcd.org/sites/default/files/Documents/MOH/Housing%20Listing%20Photos/AVA55-9thSt.jpg","Lottery_Results_Date":"2018-03-06","Lottery_Date":"2018-03-05T19:30:00.000+0000","Lottery_Results":false,"Accepting_Online_Applications":true,"Building_Selection_Criteria":"http://sfmohcd.org/sites/default/files/Resident%20Selection%20Criteria/Qualification%20Standards%201-31-2018.pdf","Reserved_community_minimum_age":0,"hasWaitlist":false,"Id":"a0W0P00000F8EVwUAN","imageURL":"http://sfmohcd.org/sites/default/files/Documents/MOH/Housing%20Listing%20Photos/AVA55-9thSt.jpg"},{"unitSummaries":{"reserved":null,"general":[{"unitType":"1 BR","totalUnits":1,"priorities":null,"minSquareFt":518,"minRentalMinIncome":2428.0,"minPercentIncome":null,"minOccupancy":1,"minMonthlyRent":1214.0,"maxSquareFt":518,"maxRentalMinIncome":2428.0,"maxPercentIncome":null,"maxOccupancy":3,"maxMonthlyRent":1214.0,"listingID":"a0W0P00000F8EV3UAN"},{"unitType":"3 BR","totalUnits":1,"priorities":null,"minSquareFt":1031,"minRentalMinIncome":2956.0,"minPercentIncome":null,"minOccupancy":3,"minMonthlyRent":1478.0,"maxSquareFt":1031,"maxRentalMinIncome":2956.0,"maxPercentIncome":null,"maxOccupancy":7,"maxMonthlyRent":1478.0,"listingID":"a0W0P00000F8EV3UAN"}]},"reservedDescriptor":null,"prioritiesDescriptor":null,"listingID":"a0W0P00000F8EV3UAN","Name":"The Gantry Units 208 and 215","Units_Available":2,"Building_Name":"The Gantry","Building_Street_Address":"2121 Third Street","Building_City":"San Francisco","Building_State":"CA","Building_Zip_Code":"94107","LastModifiedDate":"2018-02-26T21:33:56.000+0000","Application_Due_Date":"2018-02-13T01:00:00.000+0000","Building_URL":"http://www.socketsite.com/wp-content/uploads/2011/09/2121-3rd-Street-Rendering.jpg","Lottery_Results_Date":"2018-03-02","Lottery_Date":"2018-03-01T23:30:00.000+0000","Lottery_Results":false,"Accepting_Online_Applications":true,"Building_Selection_Criteria":"http://sfmohcd.org/sites/default/files/Resident%20Selection%20Criteria/RQA%20-%20Affordable%20San%20Francisco%20-%2001.02.2018.pdf","Reserved_community_minimum_age":0,"hasWaitlist":false,"Id":"a0W0P00000F8EV3UAN","imageURL":"http://www.socketsite.com/wp-content/uploads/2011/09/2121-3rd-Street-Rendering.jpg"},{"unitSummaries":{"reserved":null,"general":[{"unitType":"SRO","totalUnits":2,"priorities":null,"minSquareFt":280,"minRentalMinIncome":1537.5,"minPercentIncome":null,"minOccupancy":1,"minMonthlyRent":1025.0,"maxSquareFt":380,"maxRentalMinIncome":1612.5,"maxPercentIncome":null,"maxOccupancy":1,"maxMonthlyRent":1075.0,"listingID":"a0W0P00000F7t4uUAB"}]},"reservedDescriptor":null,"prioritiesDescriptor":null,"listingID":"a0W0P00000F7t4uUAB","Name":"Merry Go Round Shared Housing","Units_Available":2,"Building_Name":"Merry Go Round Shared Housing","Building_Street_Address":"2976 23rd Street","Building_City":"San Francisco","Building_State":"CA","Building_Zip_Code":"94110","LastModifiedDate":"2018-02-24T06:18:45.000+0000","Application_Due_Date":"2018-02-08T01:00:00.000+0000","Building_URL":"http://sfmohcd.org/sites/default/files/Documents/MOH/Housing%20Listing%20Photos/_MerryGoRound_3096-M.jpg","Lottery_Results_Date":"2018-03-01","Lottery_Date":"2018-02-28T22:00:00.000+0000","Lottery_Results":false,"Accepting_Online_Applications":true,"Building_Selection_Criteria":"http://sfmohcd.org/sites/default/files/Resident%20Selection%20Criteria/RESIDENT%20SELECTION%20CRITERIIA.pdf","Reserved_community_minimum_age":0,"hasWaitlist":false,"Id":"a0W0P00000F7t4uUAB","imageURL":"http://sfmohcd.org/sites/default/files/Documents/MOH/Housing%20Listing%20Photos/_MerryGoRound_3096-M.jpg"},{"unitSummaries":{"reserved":null,"general":[{"unitType":"1 BR","totalUnits":8,"priorities":null,"minSquareFt":610,"minRentalMinIncome":2698.0,"minPercentIncome":null,"minOccupancy":1,"minMonthlyRent":1349.0,"maxSquareFt":610,"maxRentalMinIncome":2698.0,"maxPercentIncome":null,"maxOccupancy":3,"maxMonthlyRent":1349.0,"listingID":"a0W0P00000F7wvrUAB"}]},"reservedDescriptor":null,"prioritiesDescriptor":null,"listingID":"a0W0P00000F7wvrUAB","Name":"Pierce Street Apartments","Units_Available":0,"Building_Name":"Pierce Street Apartments","Building_Street_Address":"220 Pierce Street","Building_City":"San Francisco","Building_State":"CA","Building_Zip_Code":"94117","LastModifiedDate":"2018-02-21T15:55:12.000+0000","Application_Due_Date":"2018-01-31T01:00:00.000+0000","Building_URL":"http://sfmohcd.org/sites/default/files/Documents/MOH/Housing%20Listing%20Photos/Pierce%20Front%20of%20Building.jpg","Lottery_Results_Date":"2018-02-20","Lottery_Date":"2018-02-20T21:30:00.000+0000","Lottery_Results":true,"Accepting_Online_Applications":true,"Building_Selection_Criteria":"http://sfmohcd.org/sites/default/files/Resident%20Selection%20Criteria/RSC%20%20%20-%20Pierce%20St.%20Apartments%20FINAL%20-%201.12.18.pdf","Reserved_community_minimum_age":0,"hasWaitlist":true,"Id":"a0W0P00000F7wvrUAB","imageURL":"http://sfmohcd.org/sites/default/files/Documents/MOH/Housing%20Listing%20Photos/Pierce%20Front%20of%20Building.jpg"},{"unitSummaries":{"reserved":null,"general":[{"unitType":"2 BR","totalUnits":12,"priorities":null,"minSquareFt":725,"minRentalMinIncome":838.0,"minPercentIncome":null,"minOccupancy":2,"minMonthlyRent":419.0,"maxSquareFt":725,"maxRentalMinIncome":2912.0,"maxPercentIncome":null,"maxOccupancy":5,"maxMonthlyRent":1456.0,"listingID":"a0W0P00000F7wzCUAR"}]},"reservedDescriptor":null,"prioritiesDescriptor":null,"listingID":"a0W0P00000F7wzCUAR","Name":"Howard Street Apartments","Units_Available":0,"Building_Name":"Howard Street Apartments","Building_Street_Address":"1601-1617 Howard Street","Building_City":"San Francisco","Building_State":"CA","Building_Zip_Code":"94103","LastModifiedDate":"2018-02-24T22:58:51.000+0000","Application_Due_Date":"2018-01-31T01:00:00.000+0000","Building_URL":"http://sfmohcd.org/sites/default/files/Documents/MOH/Housing%20Listing%20Photos/Howard%20front%20of%20Building.jpg","Lottery_Results_Date":"2018-02-23","Lottery_Date":"2018-02-23T21:30:00.000+0000","Lottery_Results":true,"Accepting_Online_Applications":true,"Building_Selection_Criteria":"http://sfmohcd.org/sites/default/files/Resident%20Selection%20Criteria/RSC%20%20FINAL%20-%20Howard%20St.%20Apartments%20-%2001%2011%202018.pdf","Reserved_community_minimum_age":0,"hasWaitlist":true,"Id":"a0W0P00000F7wzCUAR","imageURL":"http://sfmohcd.org/sites/default/files/Documents/MOH/Housing%20Listing%20Photos/Howard%20front%20of%20Building.jpg"},{"unitSummaries":{"reserved":null,"general":[{"unitType":"1 BR","totalUnits":1,"priorities":null,"minSquareFt":380,"minRentalMinIncome":3460.0,"minPercentIncome":null,"minOccupancy":1,"minMonthlyRent":1384.0,"maxSquareFt":380,"maxRentalMinIncome":3460.0,"maxPercentIncome":null,"maxOccupancy":3,"maxMonthlyRent":1384.0,"listingID":"a0W0P00000F80OGUAZ"}]},"reservedDescriptor":null,"prioritiesDescriptor":null,"listingID":"a0W0P00000F80OGUAZ","Name":"Glasdore Lofts Unit 504","Units_Available":1,"Building_Name":"Glasdore Lofts","Building_Street_Address":"30 Dore St","Building_City":"San Francisco","Building_State":"CA","Building_Zip_Code":"94103","LastModifiedDate":"2018-02-26T21:36:11.000+0000","Application_Due_Date":"2018-01-26T01:00:00.000+0000","Building_URL":"http://sfmohcd.org/sites/default/files/Documents/MOH/Housing%20Listing%20Photos/30DoreUnit104Rerental11-2016.jpg","Lottery_Results_Date":"2018-02-15","Lottery_Date":"2018-02-14T19:30:00.000+0000","Lottery_Results":true,"Accepting_Online_Applications":true,"Building_Selection_Criteria":"http://sfmohcd.org/sites/default/files/Resident%20Selection%20Criteria/GlasDore%20Selection%20Criteria%20FINAL%201.11.18.pdf","Reserved_community_minimum_age":0,"hasWaitlist":false,"Id":"a0W0P00000F80OGUAZ","imageURL":"http://sfmohcd.org/sites/default/files/Documents/MOH/Housing%20Listing%20Photos/30DoreUnit104Rerental11-2016.jpg"},{"unitSummaries":{"reserved":null,"general":[{"unitType":"Studio","totalUnits":44,"priorities":null,"minSquareFt":360,"minRentalMinIncome":1954.0,"minPercentIncome":null,"minOccupancy":1,"minMonthlyRent":977.0,"maxSquareFt":360,"maxRentalMinIncome":2356.0,"maxPercentIncome":null,"maxOccupancy":2,"maxMonthlyRent":1178.0,"listingID":"a0W0P00000F7qeDUAR"},{"unitType":"1 BR","totalUnits":2,"priorities":null,"minSquareFt":625,"minRentalMinIncome":2692.0,"minPercentIncome":null,"minOccupancy":1,"minMonthlyRent":1346.0,"maxSquareFt":625,"maxRentalMinIncome":2692.0,"maxPercentIncome":null,"maxOccupancy":3,"maxMonthlyRent":1346.0,"listingID":"a0W0P00000F7qeDUAR"}]},"reservedDescriptor":null,"prioritiesDescriptor":null,"listingID":"a0W0P00000F7qeDUAR","Name":"Plaza Ramona Apartments","Units_Available":0,"Building_Name":"Plaza Ramona","Building_Street_Address":"250-260 McAllister Street","Building_City":"San Francisco","Building_State":"CA","Building_Zip_Code":"94102","LastModifiedDate":"2018-02-21T15:55:04.000+0000","Application_Due_Date":"2018-01-24T01:00:00.000+0000","Building_URL":"http://sfmohcd.org/sites/default/files/Documents/MOH/Housing%20Listing%20Photos/Plaza%20Ramona%20Image.jpg","Lottery_Results_Date":"2018-02-13","Lottery_Date":"2018-02-13T21:30:00.000+0000","Lottery_Results":true,"Accepting_Online_Applications":true,"Building_Selection_Criteria":"http://sfmohcd.org/sites/default/files/Resident%20Selection%20Criteria/RSC%20Plaza%20Ramona%20-%2001%2009%202018.pdf","Reserved_community_minimum_age":0,"hasWaitlist":true,"Id":"a0W0P00000F7qeDUAR","imageURL":"http://sfmohcd.org/sites/default/files/Documents/MOH/Housing%20Listing%20Photos/Plaza%20Ramona%20Image.jpg"},{"unitSummaries":{"reserved":null,"general":[{"unitType":"1 BR","totalUnits":9,"priorities":null,"minSquareFt":600,"minRentalMinIncome":3614.0,"minPercentIncome":null,"minOccupancy":1,"minMonthlyRent":1807.0,"maxSquareFt":600,"maxRentalMinIncome":3614.0,"maxPercentIncome":null,"maxOccupancy":3,"maxMonthlyRent":1807.0,"listingID":"a0W0P00000F7qhMUAR"},{"unitType":"2 BR","totalUnits":2,"priorities":null,"minSquareFt":800,"minRentalMinIncome":4038.0,"minPercentIncome":null,"minOccupancy":2,"minMonthlyRent":2019.0,"maxSquareFt":800,"maxRentalMinIncome":4038.0,"maxPercentIncome":null,"maxOccupancy":5,"maxMonthlyRent":2019.0,"listingID":"a0W0P00000F7qhMUAR"}]},"reservedDescriptor":null,"prioritiesDescriptor":null,"listingID":"a0W0P00000F7qhMUAR","Name":"Haight Street Apartments","Units_Available":0,"Building_Name":"Haight Street Apartments","Building_Street_Address":"398 Haight Street","Building_City":"San Francisco","Building_State":"CA","Building_Zip_Code":"94102","LastModifiedDate":"2018-02-21T15:55:07.000+0000","Application_Due_Date":"2018-01-24T01:00:00.000+0000","Building_URL":"http://sfmohcd.org/sites/default/files/Documents/MOH/Housing%20Listing%20Photos/Haight%20St%20Image.jpg","Lottery_Results_Date":"2018-02-15","Lottery_Date":"2018-02-15T21:30:00.000+0000","Lottery_Results":true,"Accepting_Online_Applications":true,"Building_Selection_Criteria":"http://sfmohcd.org/sites/default/files/Resident%20Selection%20Criteria/RSC%20Haight%20St.%20Apartments%20%2001%2009%202018.pdf","Reserved_community_minimum_age":0,"hasWaitlist":true,"Id":"a0W0P00000F7qhMUAR","imageURL":"http://sfmohcd.org/sites/default/files/Documents/MOH/Housing%20Listing%20Photos/Haight%20St%20Image.jpg"},{"unitSummaries":{"reserved":null,"general":[{"unitType":"1 BR","totalUnits":12,"priorities":null,"minSquareFt":624,"minRentalMinIncome":2170.0,"minPercentIncome":null,"minOccupancy":1,"minMonthlyRent":1085.0,"maxSquareFt":685,"maxRentalMinIncome":2170.0,"maxPercentIncome":null,"maxOccupancy":3,"maxMonthlyRent":1085.0,"listingID":"a0W0P00000F7GabUAF"},{"unitType":"2 BR","totalUnits":13,"priorities":null,"minSquareFt":898,"minRentalMinIncome":2410.0,"minPercentIncome":null,"minOccupancy":2,"minMonthlyRent":1205.0,"maxSquareFt":1022,"maxRentalMinIncome":2410.0,"maxPercentIncome":null,"maxOccupancy":5,"maxMonthlyRent":1205.0,"listingID":"a0W0P00000F7GabUAF"},{"unitType":"3 BR","totalUnits":3,"priorities":null,"minSquareFt":1229,"minRentalMinIncome":2622.0,"minPercentIncome":null,"minOccupancy":3,"minMonthlyRent":1311.0,"maxSquareFt":1520,"maxRentalMinIncome":2622.0,"maxPercentIncome":null,"maxOccupancy":7,"maxMonthlyRent":1311.0,"listingID":"a0W0P00000F7GabUAF"}]},"reservedDescriptor":null,"prioritiesDescriptor":[{"shortDescription":null,"numberOfUnits":5,"name":"Mobility impaired","listingId":"a0W0P00000F7GabUAF"},{"shortDescription":null,"numberOfUnits":2,"name":"Hearing/Vision impaired","listingId":"a0W0P00000F7GabUAF"}],"listingID":"a0W0P00000F7GabUAF","Name":"Alice Griffith Apartments Phase 3","Units_Available":28,"Building_Name":"Alice Griffith Apartments Phase 3","Building_Street_Address":"2500 Arelious Walker Drive","Building_City":"San Francisco","Building_State":"CA","Building_Zip_Code":"94124","LastModifiedDate":"2018-02-27T03:03:17.000+0000","Application_Due_Date":"2017-12-23T01:00:00.000+0000","Building_URL":"http://sfmohcd.org/sites/default/files/Documents/MOH/Housing%20Listing%20Photos/photo%20AG.jpg","Lottery_Results_Date":"2018-01-20","Lottery_Date":"2018-01-18T18:00:00.000+0000","Lottery_Results":true,"Accepting_Online_Applications":false,"Building_Selection_Criteria":"http://sfmohcd.org/sites/default/files/Resident%20Selection%20Criteria/AG%20RESIDENT%20SELECTION%20PLAN%20MKTG%20PLAN%2011.15.pdf","Reserved_community_minimum_age":0,"hasWaitlist":true,"Id":"a0W0P00000F7GabUAF","imageURL":"http://sfmohcd.org/sites/default/files/Documents/MOH/Housing%20Listing%20Photos/photo%20AG.jpg"},{"unitSummaries":{"reserved":null,"general":[{"unitType":"Studio","totalUnits":2,"priorities":null,"minSquareFt":400,"minRentalMinIncome":1200.0,"minPercentIncome":null,"minOccupancy":1,"minMonthlyRent":800.0,"maxSquareFt":400,"maxRentalMinIncome":1200.0,"maxPercentIncome":null,"maxOccupancy":2,"maxMonthlyRent":800.0,"listingID":"a0W0P00000F7VYTUA3"}]},"reservedDescriptor":null,"prioritiesDescriptor":null,"listingID":"a0W0P00000F7VYTUA3","Name":"Sister Bernie Galvin Apartments Units 206 211","Units_Available":2,"Building_Name":"Sister Bernie Galvin Apartments","Building_Street_Address":"785 Brannan Street","Building_City":"San Francisco","Building_State":"CA","Building_Zip_Code":"94103","LastModifiedDate":"2018-02-24T00:26:45.000+0000","Application_Due_Date":"2017-12-22T01:00:00.000+0000","Building_URL":"http://sfmohcd.org/sites/default/files/Documents/MOH/Housing%20Listing%20Photos/Gavin%20Apts%20-%20785%20Brannan.jpg","Lottery_Results_Date":"2018-01-17","Lottery_Date":"2018-01-16T19:00:00.000+0000","Lottery_Results":true,"Accepting_Online_Applications":true,"Building_Selection_Criteria":"http://sfmohcd.org/sites/default/files/Resident%20Selection%20Criteria/Galvin%20Rental%20Criteria%20%2012-12-17.pdf","Reserved_community_minimum_age":0,"hasWaitlist":false,"Id":"a0W0P00000F7VYTUA3","imageURL":"http://sfmohcd.org/sites/default/files/Documents/MOH/Housing%20Listing%20Photos/Gavin%20Apts%20-%20785%20Brannan.jpg"},{"unitSummaries":{"reserved":null,"general":[{"unitType":"Studio","totalUnits":25,"priorities":null,"minSquareFt":300,"minRentalMinIncome":3148.0,"minPercentIncome":null,"minOccupancy":1,"minMonthlyRent":1574.0,"maxSquareFt":527,"maxRentalMinIncome":4720.0,"maxPercentIncome":null,"maxOccupancy":2,"maxMonthlyRent":2360.0,"listingID":"a0W0P00000F7PB3UAN"},{"unitType":"1 BR","totalUnits":39,"priorities":null,"minSquareFt":502,"minRentalMinIncome":3596.0,"minPercentIncome":null,"minOccupancy":1,"minMonthlyRent":1798.0,"maxSquareFt":652,"maxRentalMinIncome":5398.0,"maxPercentIncome":null,"maxOccupancy":3,"maxMonthlyRent":2699.0,"listingID":"a0W0P00000F7PB3UAN"},{"unitType":"2 BR","totalUnits":12,"priorities":null,"minSquareFt":799,"minRentalMinIncome":4046.0,"minPercentIncome":null,"minOccupancy":2,"minMonthlyRent":2023.0,"maxSquareFt":886,"maxRentalMinIncome":6744.0,"maxPercentIncome":null,"maxOccupancy":5,"maxMonthlyRent":3372.0,"listingID":"a0W0P00000F7PB3UAN"}]},"reservedDescriptor":null,"prioritiesDescriptor":null,"listingID":"a0W0P00000F7PB3UAN","Name":"Carmel Rincon","Units_Available":0,"Building_Name":"Carmel Rincon","Building_Street_Address":"88 Howard Street","Building_City":"San Francisco","Building_State":"CA","Building_Zip_Code":"94105","LastModifiedDate":"2018-02-21T15:54:49.000+0000","Application_Due_Date":"2017-12-22T01:00:00.000+0000","Building_URL":"http://sfmohcd.org/sites/default/files/Documents/MOH/Housing%20Listing%20Photos/Carmel%20Rincon.jpg","Lottery_Results_Date":"2018-01-11","Lottery_Date":"2018-01-11T22:00:00.000+0000","Lottery_Results":true,"Accepting_Online_Applications":true,"Building_Selection_Criteria":"http://sfmohcd.org/sites/default/files/Resident%20Selection%20Criteria/Carmel%20Rincon%20-%20RSC.pdf","Reserved_community_minimum_age":0,"hasWaitlist":true,"Id":"a0W0P00000F7PB3UAN","imageURL":"http://sfmohcd.org/sites/default/files/Documents/MOH/Housing%20Listing%20Photos/Carmel%20Rincon.jpg"},{"unitSummaries":{"reserved":null,"general":[{"unitType":"1 BR","totalUnits":1,"priorities":null,"minSquareFt":500,"minRentalMinIncome":1202.0,"minPercentIncome":null,"minOccupancy":1,"minMonthlyRent":601.0,"maxSquareFt":500,"maxRentalMinIncome":1202.0,"maxPercentIncome":null,"maxOccupancy":3,"maxMonthlyRent":601.0,"listingID":"a0W0P00000F7FLxUAN"}]},"reservedDescriptor":null,"prioritiesDescriptor":null,"listingID":"a0W0P00000F7FLxUAN","Name":"Arc Light Unit 307","Units_Available":1,"Building_Name":"Arc Light","Building_Street_Address":"21 Clarence Place","Building_City":"San Francisco","Building_State":"CA","Building_Zip_Code":"94107","LastModifiedDate":"2018-02-22T20:07:47.000+0000","Application_Due_Date":"2017-11-22T01:00:00.000+0000","Building_URL":"http://sfmohcd.org/sites/default/files/Documents/MOH/Housing%20Listing%20Photos/21ClarencePlace-ArcLight.jpg","Lottery_Results_Date":"2017-12-13","Lottery_Date":"2017-12-13T21:30:00.000+0000","Lottery_Results":true,"Accepting_Online_Applications":true,"Building_Selection_Criteria":"http://sfmohcd.org/sites/default/files/Resident%20Selection%20Criteria/Resident%20selection%20criteria-Arc%20Light%2011-1-17.pdf","Reserved_community_minimum_age":0,"hasWaitlist":false,"Id":"a0W0P00000F7FLxUAN","imageURL":"http://sfmohcd.org/sites/default/files/Documents/MOH/Housing%20Listing%20Photos/21ClarencePlace-ArcLight.jpg"},{"unitSummaries":{"reserved":null,"general":[{"unitType":"1 BR","totalUnits":3,"priorities":null,"minSquareFt":567,"minRentalMinIncome":3322.5,"minPercentIncome":null,"minOccupancy":1,"minMonthlyRent":1329.0,"maxSquareFt":590,"maxRentalMinIncome":3322.5,"maxPercentIncome":null,"maxOccupancy":3,"maxMonthlyRent":1329.0,"listingID":"a0W0P00000F6wytUAB"},{"unitType":"2 BR","totalUnits":2,"priorities":null,"minSquareFt":864,"minRentalMinIncome":3707.5,"minPercentIncome":null,"minOccupancy":2,"minMonthlyRent":1483.0,"maxSquareFt":871,"maxRentalMinIncome":3707.5,"maxPercentIncome":null,"maxOccupancy":5,"maxMonthlyRent":1483.0,"listingID":"a0W0P00000F6wytUAB"}]},"reservedDescriptor":null,"prioritiesDescriptor":null,"listingID":"a0W0P00000F6wytUAB","Name":"3000 23rd Street","Units_Available":5,"Building_Name":"3000 23rd Street","Building_Street_Address":"3000 23rd Street","Building_City":"San Francisco","Building_State":"CA","Building_Zip_Code":"94110","LastModifiedDate":"2018-02-21T15:54:13.000+0000","Application_Due_Date":"2017-11-08T01:00:00.000+0000","Building_URL":"http://sfmohcd.org/sites/default/files/Documents/MOH/Housing%20Listing%20Photos/3000%2023rd.jpg","Lottery_Results_Date":"2017-12-05","Lottery_Date":"2017-12-05T18:00:00.000+0000","Lottery_Results":true,"Accepting_Online_Applications":true,"Building_Selection_Criteria":"http://sfmohcd.org/sites/default/files/Resident%20Selection%20Criteria/RSC%20Winfield%2009.27.17.pdf","Reserved_community_minimum_age":0,"hasWaitlist":false,"Id":"a0W0P00000F6wytUAB","imageURL":"http://sfmohcd.org/sites/default/files/Documents/MOH/Housing%20Listing%20Photos/3000%2023rd.jpg"},{"unitSummaries":{"reserved":null,"general":[{"unitType":"Studio","totalUnits":6,"priorities":null,"minSquareFt":559,"minRentalMinIncome":3800.0,"minPercentIncome":null,"minOccupancy":1,"minMonthlyRent":1900.0,"maxSquareFt":559,"maxRentalMinIncome":3800.0,"maxPercentIncome":null,"maxOccupancy":2,"maxMonthlyRent":1900.0,"listingID":"a0W0P00000F71xyUAB"},{"unitType":"1 BR","totalUnits":1,"priorities":null,"minSquareFt":710,"minRentalMinIncome":4200.0,"minPercentIncome":null,"minOccupancy":1,"minMonthlyRent":2100.0,"maxSquareFt":710,"maxRentalMinIncome":4200.0,"maxPercentIncome":null,"maxOccupancy":3,"maxMonthlyRent":2100.0,"listingID":"a0W0P00000F71xyUAB"}]},"reservedDescriptor":null,"prioritiesDescriptor":null,"listingID":"a0W0P00000F71xyUAB","Name":"Metro @ Showplace Square","Units_Available":7,"Building_Name":"Metro @Showplace Square","Building_Street_Address":"660 King Street","Building_City":"San Francisco","Building_State":"CA","Building_Zip_Code":"94107","LastModifiedDate":"2018-02-21T15:54:28.000+0000","Application_Due_Date":"2017-11-08T01:00:00.000+0000","Building_URL":"http://sfmohcd.org/sites/default/files/Documents/MOH/Housing%20Listing%20Photos/MetroAtShowplaceSquare-%20660%20King.jpg","Lottery_Results_Date":"2017-12-09","Lottery_Date":"2017-12-08T19:30:00.000+0000","Lottery_Results":true,"Accepting_Online_Applications":true,"Building_Selection_Criteria":"http://sfmohcd.org/sites/default/files/Resident%20Selection%20Criteria/Final%20Basics%20for%20Denial-Building%20Rental%20Requirements-%20BMR%20%28002%29.pdf","Reserved_community_minimum_age":0,"hasWaitlist":false,"Id":"a0W0P00000F71xyUAB","imageURL":"http://sfmohcd.org/sites/default/files/Documents/MOH/Housing%20Listing%20Photos/MetroAtShowplaceSquare-%20660%20King.jpg"},{"unitSummaries":{"reserved":null,"general":[{"unitType":"Studio","totalUnits":29,"priorities":null,"minSquareFt":350,"minRentalMinIncome":1382.0,"minPercentIncome":null,"minOccupancy":1,"minMonthlyRent":691.0,"maxSquareFt":378,"maxRentalMinIncome":2018.0,"maxPercentIncome":null,"maxOccupancy":2,"maxMonthlyRent":1009.0,"listingID":"a0W0P00000F72I4UAJ"}]},"reservedDescriptor":null,"prioritiesDescriptor":[{"shortDescription":null,"numberOfUnits":2,"name":"Mobility impaired","listingId":"a0W0P00000F72I4UAJ"}],"listingID":"a0W0P00000F72I4UAJ","Name":"Madonna Residences","Units_Available":4,"Building_Name":"Madonna Residences","Building_Street_Address":"350 Golden Gate","Building_City":"San Francisco","Building_State":"CA","Building_Zip_Code":"94102","LastModifiedDate":"2018-02-21T15:54:30.000+0000","Application_Due_Date":"2017-11-07T01:00:00.000+0000","Building_URL":"http://sfmohcd.org/sites/default/files/Documents/MOH/Housing%20Listing%20Photos/Madonna.jpg","Lottery_Results_Date":"2017-12-01","Lottery_Date":"2017-12-01T22:00:00.000+0000","Lottery_Results":true,"Accepting_Online_Applications":true,"Building_Selection_Criteria":"http://sfmohcd.org/sites/default/files/Resident%20Selection%20Criteria/Madonna%20Resident%20Selection%20Critera%2010-18-17.pdf","Reserved_community_minimum_age":0,"hasWaitlist":true,"Id":"a0W0P00000F72I4UAJ","imageURL":"http://sfmohcd.org/sites/default/files/Documents/MOH/Housing%20Listing%20Photos/Madonna.jpg"},{"unitSummaries":{"reserved":null,"general":[{"unitType":"1 BR","totalUnits":1,"priorities":null,"minSquareFt":643,"minRentalMinIncome":3035.0,"minPercentIncome":null,"minOccupancy":1,"minMonthlyRent":1214.0,"maxSquareFt":643,"maxRentalMinIncome":3035.0,"maxPercentIncome":null,"maxOccupancy":3,"maxMonthlyRent":1214.0,"listingID":"a0W0P00000F74dwUAB"}]},"reservedDescriptor":null,"prioritiesDescriptor":null,"listingID":"a0W0P00000F74dwUAB","Name":"Alchemy by Alta Unit 177","Units_Available":1,"Building_Name":"Alchemy By Alta","Building_Street_Address":"200 Buchanan St","Building_City":"San Francisco","Building_State":"CA","Building_Zip_Code":"94102","LastModifiedDate":"2018-02-21T15:54:34.000+0000","Application_Due_Date":"2017-11-07T01:00:00.000+0000","Building_URL":"http://sfmohcd.org/sites/default/files/Documents/MOH/Housing%20Listing%20Photos/Alchemy-200-Buchanan.jpg","Lottery_Results_Date":"2017-11-20","Lottery_Date":"2017-11-20T19:00:00.000+0000","Lottery_Results":true,"Accepting_Online_Applications":true,"Building_Selection_Criteria":"http://sfmohcd.org/sites/default/files/Resident%20Selection%20Criteria/Alchemy%20Screening%20Criteria1.pdf","Reserved_community_minimum_age":0,"hasWaitlist":false,"Id":"a0W0P00000F74dwUAB","imageURL":"http://sfmohcd.org/sites/default/files/Documents/MOH/Housing%20Listing%20Photos/Alchemy-200-Buchanan.jpg"},{"unitSummaries":{"reserved":null,"general":[{"unitType":"Studio","totalUnits":4,"priorities":null,"minSquareFt":378,"minRentalMinIncome":2657.5,"minPercentIncome":null,"minOccupancy":1,"minMonthlyRent":1063.0,"maxSquareFt":397,"maxRentalMinIncome":2657.5,"maxPercentIncome":null,"maxOccupancy":2,"maxMonthlyRent":1063.0,"listingID":"a0W0P00000F6sliUAB"},{"unitType":"1 BR","totalUnits":2,"priorities":null,"minSquareFt":496,"minRentalMinIncome":3035.0,"minPercentIncome":null,"minOccupancy":1,"minMonthlyRent":1214.0,"maxSquareFt":496,"maxRentalMinIncome":3035.0,"maxPercentIncome":null,"maxOccupancy":3,"maxMonthlyRent":1214.0,"listingID":"a0W0P00000F6sliUAB"}]},"reservedDescriptor":null,"prioritiesDescriptor":null,"listingID":"a0W0P00000F6sliUAB","Name":"570 Jessie","Units_Available":6,"Building_Name":"570 Jessie","Building_Street_Address":"570 Jessie Street","Building_City":"San Francisco","Building_State":"CA","Building_Zip_Code":"94103","LastModifiedDate":"2018-02-21T15:54:08.000+0000","Application_Due_Date":"2017-10-31T00:00:00.000+0000","Building_URL":"http://sfmohcd.org/sites/default/files/Documents/MOH/Housing%20Listing%20Photos/570-jessie-photo.jpg","Lottery_Results_Date":"2017-11-30","Lottery_Date":"2017-11-30T23:30:00.000+0000","Lottery_Results":true,"Accepting_Online_Applications":true,"Building_Selection_Criteria":"http://sfmohcd.org/sites/default/files/Resident%20Selection%20Criteria/A.%20VFORM%20-%20Rental%20Policy%20FINAL.pdf","Reserved_community_minimum_age":0,"hasWaitlist":false,"Id":"a0W0P00000F6sliUAB","imageURL":"http://sfmohcd.org/sites/default/files/Documents/MOH/Housing%20Listing%20Photos/570-jessie-photo.jpg"},{"unitSummaries":{"reserved":null,"general":[{"unitType":"Studio","totalUnits":3,"priorities":null,"minSquareFt":478,"minRentalMinIncome":2126.0,"minPercentIncome":null,"minOccupancy":1,"minMonthlyRent":1063.0,"maxSquareFt":488,"maxRentalMinIncome":2126.0,"maxPercentIncome":null,"maxOccupancy":2,"maxMonthlyRent":1063.0,"listingID":"a0W0P00000F6zCdUAJ"},{"unitType":"1 BR","totalUnits":3,"priorities":null,"minSquareFt":500,"minRentalMinIncome":2428.0,"minPercentIncome":null,"minOccupancy":1,"minMonthlyRent":1214.0,"maxSquareFt":548,"maxRentalMinIncome":2428.0,"maxPercentIncome":null,"maxOccupancy":3,"maxMonthlyRent":1214.0,"listingID":"a0W0P00000F6zCdUAJ"}]},"reservedDescriptor":null,"prioritiesDescriptor":null,"listingID":"a0W0P00000F6zCdUAJ","Name":"Trinity Place Phase 2 Units 409 522 606 724 922 1408","Units_Available":6,"Building_Name":"Trinity Place Phase 2","Building_Street_Address":"1190 Mission Street","Building_City":"San Francisco","Building_State":"CA","Building_Zip_Code":"94103","LastModifiedDate":"2018-02-21T15:54:21.000+0000","Application_Due_Date":"2017-10-25T00:00:00.000+0000","Building_URL":"http://sfmohcd.org/sites/default/files/Documents/MOH/Housing%20Listing%20Photos/Trinity%20Place%201188%20Mission.jpg","Lottery_Results_Date":"2017-11-14","Lottery_Date":"2017-11-13T19:00:00.000+0000","Lottery_Results":true,"Accepting_Online_Applications":true,"Building_Selection_Criteria":"http://sfmohcd.org/sites/default/files/Resident%20Selection%20Criteria/TRINITY%201%20%202%20-%20RESIDENT%20SELECTION%20PLAN%20-%20FAIR%20CHANCE%20ORDINANCE%20%282017%29BM.pdf","Reserved_community_minimum_age":0,"hasWaitlist":false,"Id":"a0W0P00000F6zCdUAJ","imageURL":"http://sfmohcd.org/sites/default/files/Documents/MOH/Housing%20Listing%20Photos/Trinity%20Place%201188%20Mission.jpg"},{"unitSummaries":{"reserved":null,"general":[{"unitType":"Studio","totalUnits":1,"priorities":null,"minSquareFt":476,"minRentalMinIncome":2657.5,"minPercentIncome":null,"minOccupancy":1,"minMonthlyRent":1063.0,"maxSquareFt":476,"maxRentalMinIncome":2657.5,"maxPercentIncome":null,"maxOccupancy":2,"maxMonthlyRent":1063.0,"listingID":"a0W0P00000F6zDoUAJ"},{"unitType":"1 BR","totalUnits":1,"priorities":null,"minSquareFt":788,"minRentalMinIncome":3035.0,"minPercentIncome":null,"minOccupancy":1,"minMonthlyRent":1214.0,"maxSquareFt":788,"maxRentalMinIncome":3035.0,"maxPercentIncome":null,"maxOccupancy":3,"maxMonthlyRent":1214.0,"listingID":"a0W0P00000F6zDoUAJ"},{"unitType":"2 BR","totalUnits":1,"priorities":null,"minSquareFt":1106,"minRentalMinIncome":3382.5,"minPercentIncome":null,"minOccupancy":2,"minMonthlyRent":1353.0,"maxSquareFt":1106,"maxRentalMinIncome":3382.5,"maxPercentIncome":null,"maxOccupancy":5,"maxMonthlyRent":1353.0,"listingID":"a0W0P00000F6zDoUAJ"}]},"reservedDescriptor":null,"prioritiesDescriptor":null,"listingID":"a0W0P00000F6zDoUAJ","Name":"NEMA Units 412, 515, 740","Units_Available":3,"Building_Name":"NEMA","Building_Street_Address":"8 Tenth Street","Building_City":"San Francisco","Building_State":"CA","Building_Zip_Code":"94103","LastModifiedDate":"2018-02-21T15:54:23.000+0000","Application_Due_Date":"2017-10-25T00:00:00.000+0000","Building_URL":"http://sfmohcd.org/sites/default/files/Documents/MOH/Housing%20Listing%20Photos/NEMA8-10thSt.jpg","Lottery_Results_Date":"2017-11-09","Lottery_Date":"2017-11-08T21:00:00.000+0000","Lottery_Results":true,"Accepting_Online_Applications":true,"Building_Selection_Criteria":"http://sfmohcd.org/sites/default/files/Resident%20Selection%20Criteria/NEMA%20-%20RESIDENT%20SELECTION%20PLAN%20-%20FAIR%20CHANCE%20ORDINANCE%20%282017%29BM.pdf","Reserved_community_minimum_age":0,"hasWaitlist":false,"Id":"a0W0P00000F6zDoUAJ","imageURL":"http://sfmohcd.org/sites/default/files/Documents/MOH/Housing%20Listing%20Photos/NEMA8-10thSt.jpg"},{"unitSummaries":{"reserved":null,"general":[{"unitType":"1 BR","totalUnits":46,"priorities":null,"minSquareFt":518,"minRentalMinIncome":1974.0,"minPercentIncome":null,"minOccupancy":1,"minMonthlyRent":987.0,"maxSquareFt":674,"maxRentalMinIncome":2468.0,"maxPercentIncome":null,"maxOccupancy":3,"maxMonthlyRent":1234.0,"listingID":"a0W0P00000F6lBXUAZ"},{"unitType":"2 BR","totalUnits":35,"priorities":null,"minSquareFt":755,"minRentalMinIncome":2370.0,"minPercentIncome":null,"minOccupancy":2,"minMonthlyRent":1185.0,"maxSquareFt":884,"maxRentalMinIncome":2962.0,"maxPercentIncome":null,"maxOccupancy":5,"maxMonthlyRent":1481.0,"listingID":"a0W0P00000F6lBXUAZ"},{"unitType":"3 BR","totalUnits":14,"priorities":null,"minSquareFt":1014,"minRentalMinIncome":2882.0,"minPercentIncome":null,"minOccupancy":3,"minMonthlyRent":1441.0,"maxSquareFt":1190,"maxRentalMinIncome":3422.0,"maxPercentIncome":null,"maxOccupancy":7,"maxMonthlyRent":1711.0,"listingID":"a0W0P00000F6lBXUAZ"}]},"reservedDescriptor":null,"prioritiesDescriptor":[{"shortDescription":null,"numberOfUnits":5,"name":"Hearing/Vision impaired","listingId":"a0W0P00000F6lBXUAZ"},{"shortDescription":null,"numberOfUnits":12,"name":"Mobility impaired","listingId":"a0W0P00000F6lBXUAZ"}],"listingID":"a0W0P00000F6lBXUAZ","Name":"Natalie Gubb Commons - 255 Fremont Street","Units_Available":95,"Building_Name":"Natalie Gubb Commons","Building_Street_Address":"255 Fremont Street","Building_City":"San Francisco","Building_State":"CA","Building_Zip_Code":"94105","LastModifiedDate":"2018-02-21T15:53:55.000+0000","Application_Due_Date":"2017-10-21T00:00:00.000+0000","Building_URL":"http://sfmohcd.org/sites/default/files/Documents/MOH/Housing%20Listing%20Photos/TB72.jpg","Lottery_Results_Date":"2017-11-14","Lottery_Date":"2017-11-14T18:00:00.000+0000","Lottery_Results":true,"Accepting_Online_Applications":true,"Building_Selection_Criteria":"https://www.mercyhousing.org/California/NatalieGubbCommons?","Reserved_community_minimum_age":0,"hasWaitlist":true,"Id":"a0W0P00000F6lBXUAZ","imageURL":"http://sfmohcd.org/sites/default/files/Documents/MOH/Housing%20Listing%20Photos/TB72.jpg"},{"unitSummaries":{"reserved":null,"general":[{"unitType":"1 BR","totalUnits":1,"priorities":null,"minSquareFt":782,"minRentalMinIncome":6920.0,"minPercentIncome":null,"minOccupancy":1,"minMonthlyRent":2768.0,"maxSquareFt":782,"maxRentalMinIncome":6920.0,"maxPercentIncome":null,"maxOccupancy":3,"maxMonthlyRent":2768.0,"listingID":"a0W0P00000F6xY9UAJ"}]},"reservedDescriptor":null,"prioritiesDescriptor":null,"listingID":"a0W0P00000F6xY9UAJ","Name":"388 Beale Unit 906","Units_Available":1,"Building_Name":"388 Beale","Building_Street_Address":"388 Beale Street","Building_City":"San Francisco","Building_State":"CA","Building_Zip_Code":"94105","LastModifiedDate":"2018-02-22T22:29:35.000+0000","Application_Due_Date":"2017-10-20T00:00:00.000+0000","Building_URL":"http://sfmohcd.org/sites/default/files/Documents/MOH/Housing%20Listing%20Photos/388Beale.jpg","Lottery_Results_Date":"2017-11-07","Lottery_Date":"2017-11-07T00:00:00.000+0000","Lottery_Results":true,"Accepting_Online_Applications":true,"Building_Selection_Criteria":"http://www.udr.com/uploadedFiles/UDR3/Common/ContentPages/SF_STATEMENT_OF_RENTAL_POLICY.pdf","Reserved_community_minimum_age":0,"hasWaitlist":false,"Id":"a0W0P00000F6xY9UAJ","imageURL":"http://sfmohcd.org/sites/default/files/Documents/MOH/Housing%20Listing%20Photos/388Beale.jpg"},{"unitSummaries":{"reserved":null,"general":[{"unitType":"1 BR","totalUnits":1,"priorities":null,"minSquareFt":679,"minRentalMinIncome":2428.0,"minPercentIncome":null,"minOccupancy":1,"minMonthlyRent":1214.0,"maxSquareFt":679,"maxRentalMinIncome":2428.0,"maxPercentIncome":null,"maxOccupancy":3,"maxMonthlyRent":1214.0,"listingID":"a0W0P00000F6x2aUAB"}]},"reservedDescriptor":null,"prioritiesDescriptor":null,"listingID":"a0W0P00000F6x2aUAB","Name":"Venn Unit 412","Units_Available":1,"Building_Name":"Venn","Building_Street_Address":"1844 Market Street","Building_City":"San Francisco","Building_State":"CA","Building_Zip_Code":"94102","LastModifiedDate":"2018-02-21T15:54:17.000+0000","Application_Due_Date":"2017-10-18T00:00:00.000+0000","Building_URL":"http://www.vennonmarket.com/img/gallery/interiors/Venn07.jpg","Lottery_Results_Date":"2017-11-06","Lottery_Date":"2017-11-03T21:00:00.000+0000","Lottery_Results":true,"Accepting_Online_Applications":true,"Building_Selection_Criteria":"http://sfmohcd.org/sites/default/files/Resident%20Selection%20Criteria/The%20Venn%20Resident%20Selection%20Criteria%202017.pdf","Reserved_community_minimum_age":0,"hasWaitlist":false,"Id":"a0W0P00000F6x2aUAB","imageURL":"http://www.vennonmarket.com/img/gallery/interiors/Venn07.jpg"},{"unitSummaries":{"reserved":null,"general":[{"unitType":"Studio","totalUnits":4,"priorities":null,"minSquareFt":446,"minRentalMinIncome":2126.0,"minPercentIncome":null,"minOccupancy":1,"minMonthlyRent":1063.0,"maxSquareFt":462,"maxRentalMinIncome":2126.0,"maxPercentIncome":null,"maxOccupancy":2,"maxMonthlyRent":1063.0,"listingID":"a0W0P00000F6jneUAB"},{"unitType":"1 BR","totalUnits":3,"priorities":null,"minSquareFt":650,"minRentalMinIncome":2428.0,"minPercentIncome":null,"minOccupancy":1,"minMonthlyRent":1214.0,"maxSquareFt":667,"maxRentalMinIncome":2428.0,"maxPercentIncome":null,"maxOccupancy":3,"maxMonthlyRent":1214.0,"listingID":"a0W0P00000F6jneUAB"},{"unitType":"2 BR","totalUnits":5,"priorities":null,"minSquareFt":991,"minRentalMinIncome":2706.0,"minPercentIncome":null,"minOccupancy":2,"minMonthlyRent":1353.0,"maxSquareFt":1040,"maxRentalMinIncome":2706.0,"maxPercentIncome":null,"maxOccupancy":5,"maxMonthlyRent":1353.0,"listingID":"a0W0P00000F6jneUAB"}]},"reservedDescriptor":null,"prioritiesDescriptor":null,"listingID":"a0W0P00000F6jneUAB","Name":"The Martin","Units_Available":12,"Building_Name":"The Martin","Building_Street_Address":"2051 Third Street","Building_City":"San Francisco","Building_State":"CA","Building_Zip_Code":"94107","LastModifiedDate":"2018-02-22T17:25:31.000+0000","Application_Due_Date":"2017-10-17T00:00:00.000+0000","Building_URL":"http://sfmohcd.org/sites/default/files/Documents/MOH/Housing%20Listing%20Photos/The%20Martin%20Photo%20%282%29.jpg","Lottery_Results_Date":"2017-11-16","Lottery_Date":"2017-11-16T18:00:00.000+0000","Lottery_Results":true,"Accepting_Online_Applications":true,"Building_Selection_Criteria":"http://sfmohcd.org/sites/default/files/Resident%20Selection%20Criteria/RQA%20-%20Affordable%20-%20%20The%20Martin.pdf","Reserved_community_minimum_age":0,"hasWaitlist":false,"Id":"a0W0P00000F6jneUAB","imageURL":"http://sfmohcd.org/sites/default/files/Documents/MOH/Housing%20Listing%20Photos/The%20Martin%20Photo%20%282%29.jpg"},{"unitSummaries":{"reserved":null,"general":[{"unitType":"Studio","totalUnits":1,"priorities":null,"minSquareFt":402,"minRentalMinIncome":2126.0,"minPercentIncome":null,"minOccupancy":1,"minMonthlyRent":1063.0,"maxSquareFt":402,"maxRentalMinIncome":2126.0,"maxPercentIncome":null,"maxOccupancy":2,"maxMonthlyRent":1063.0,"listingID":"a0W0P00000F6hjuUAB"}]},"reservedDescriptor":null,"prioritiesDescriptor":null,"listingID":"a0W0P00000F6hjuUAB","Name":"Stevenson Lofts Unit 301","Units_Available":1,"Building_Name":"Stevenson Lofts","Building_Street_Address":"529 Stevenson St","Building_City":"San Francisco","Building_State":"CA","Building_Zip_Code":"94103","LastModifiedDate":"2018-02-21T15:53:48.000+0000","Application_Due_Date":"2017-09-14T00:00:00.000+0000","Building_URL":"http://sfmohcd.org/sites/default/files/Documents/MOH/Housing%20Listing%20Photos/StevensonLofts529Stevenson.jpg","Lottery_Results_Date":"2017-10-02","Lottery_Date":"2017-09-29T20:30:00.000+0000","Lottery_Results":true,"Accepting_Online_Applications":true,"Building_Selection_Criteria":"https://www.stevensonloftssf.com/building-selection-criteria/","Reserved_community_minimum_age":0,"hasWaitlist":false,"Id":"a0W0P00000F6hjuUAB","imageURL":"http://sfmohcd.org/sites/default/files/Documents/MOH/Housing%20Listing%20Photos/StevensonLofts529Stevenson.jpg"},{"unitSummaries":{"reserved":null,"general":[{"unitType":"2 BR","totalUnits":3,"priorities":null,"minSquareFt":1008,"minRentalMinIncome":3707.5,"minPercentIncome":null,"minOccupancy":2,"minMonthlyRent":1483.0,"maxSquareFt":1008,"maxRentalMinIncome":3707.5,"maxPercentIncome":null,"maxOccupancy":5,"maxMonthlyRent":1483.0,"listingID":"a0W0P00000Dh34hUAB"}]},"reservedDescriptor":null,"prioritiesDescriptor":null,"listingID":"a0W0P00000Dh34hUAB","Name":"125 Mason Units 302, 701, 706","Units_Available":3,"Building_Name":"125 Mason","Building_Street_Address":"125 Mason Street","Building_City":"San Francisco","Building_State":"CA","Building_Zip_Code":"94102","LastModifiedDate":"2018-02-21T15:53:46.000+0000","Application_Due_Date":"2017-09-07T00:00:00.000+0000","Building_URL":"http://sfmohcd.org/sites/default/files/Documents/MOH/Housing%20Listing%20Photos/125%20Mason%20Street.jpg","Lottery_Results_Date":"2017-10-03","Lottery_Date":"2017-10-02T17:00:00.000+0000","Lottery_Results":true,"Accepting_Online_Applications":true,"Building_Selection_Criteria":"http://sfmohcd.org/sites/default/files/Resident%20Selection%20Criteria/125%20resident%20selection%20Final%20%208-28-17.pdf","Reserved_community_minimum_age":0,"hasWaitlist":false,"Id":"a0W0P00000Dh34hUAB","imageURL":"http://sfmohcd.org/sites/default/files/Documents/MOH/Housing%20Listing%20Photos/125%20Mason%20Street.jpg"},{"unitSummaries":{"reserved":null,"general":[{"unitType":"1 BR","totalUnits":1,"priorities":null,"minSquareFt":825,"minRentalMinIncome":3690.0,"minPercentIncome":null,"minOccupancy":1,"minMonthlyRent":1845.0,"maxSquareFt":825,"maxRentalMinIncome":3690.0,"maxPercentIncome":null,"maxOccupancy":3,"maxMonthlyRent":1845.0,"listingID":"a0W0P00000ByBANUA3"},{"unitType":"2 BR","totalUnits":2,"priorities":null,"minSquareFt":1258,"minRentalMinIncome":4150.0,"minPercentIncome":null,"minOccupancy":2,"minMonthlyRent":2075.0,"maxSquareFt":1286,"maxRentalMinIncome":5188.0,"maxPercentIncome":null,"maxOccupancy":5,"maxMonthlyRent":2594.0,"listingID":"a0W0P00000ByBANUA3"}]},"reservedDescriptor":null,"prioritiesDescriptor":null,"listingID":"a0W0P00000ByBANUA3","Name":"388 Beale Units 716 815 1115","Units_Available":3,"Building_Name":"388 Beale","Building_Street_Address":"388 Beale Street","Building_City":"San Francisco","Building_State":"CA","Building_Zip_Code":"94105","LastModifiedDate":"2018-02-21T15:51:50.000+0000","Application_Due_Date":"2017-08-15T00:00:00.000+0000","Building_URL":"http://sfmohcd.org/sites/default/files/Documents/MOH/Housing%20Listing%20Photos/388Beale.jpg","Lottery_Results_Date":"2017-08-28","Lottery_Date":"2017-08-25T21:00:00.000+0000","Lottery_Results":true,"Accepting_Online_Applications":true,"Building_Selection_Criteria":"http://www.udr.com/uploadedFiles/UDR3/Common/ContentPages/SF_STATEMENT_OF_RENTAL_POLICY.pdf","Reserved_community_minimum_age":0,"hasWaitlist":false,"Id":"a0W0P00000ByBANUA3","imageURL":"http://sfmohcd.org/sites/default/files/Documents/MOH/Housing%20Listing%20Photos/388Beale.jpg"},{"unitSummaries":{"reserved":null,"general":[{"unitType":"2 BR","totalUnits":1,"priorities":null,"minSquareFt":983,"minRentalMinIncome":3707.5,"minPercentIncome":null,"minOccupancy":2,"minMonthlyRent":1483.0,"maxSquareFt":983,"maxRentalMinIncome":3707.5,"maxPercentIncome":null,"maxOccupancy":5,"maxMonthlyRent":1483.0,"listingID":"a0W0P00000ByD3QUAV"}]},"reservedDescriptor":null,"prioritiesDescriptor":null,"listingID":"a0W0P00000ByD3QUAV","Name":"The Lofts at One Powell Unit 501","Units_Available":1,"Building_Name":"The Loft at One Powell","Building_Street_Address":"10 Cyril Magnin Street","Building_City":"San Francisco","Building_State":"CA","Building_Zip_Code":"94102","LastModifiedDate":"2018-02-21T15:51:53.000+0000","Application_Due_Date":"2017-08-15T00:00:00.000+0000","Building_URL":"http://sfmohcd.org/sites/default/files/Documents/MOH/Housing%20Listing%20Photos/The%20Lofts%20at%20One%20Powell.jpg","Lottery_Results_Date":"2017-09-04","Lottery_Date":"2017-09-01T21:30:00.000+0000","Lottery_Results":true,"Accepting_Online_Applications":true,"Building_Selection_Criteria":"https://on-site.com/reports/web/criteria/print.pdf?criteria_set_id=0&property_id=157712","Reserved_community_minimum_age":0,"hasWaitlist":false,"Id":"a0W0P00000ByD3QUAV","imageURL":"http://sfmohcd.org/sites/default/files/Documents/MOH/Housing%20Listing%20Photos/The%20Lofts%20at%20One%20Powell.jpg"},{"unitSummaries":{"reserved":null,"general":[{"unitType":"1 BR","totalUnits":1,"priorities":null,"minSquareFt":665,"minRentalMinIncome":3035.0,"minPercentIncome":null,"minOccupancy":1,"minMonthlyRent":1214.0,"maxSquareFt":665,"maxRentalMinIncome":3035.0,"maxPercentIncome":null,"maxOccupancy":3,"maxMonthlyRent":1214.0,"listingID":"a0W0P00000BxjZpUAJ"}]},"reservedDescriptor":null,"prioritiesDescriptor":null,"listingID":"a0W0P00000BxjZpUAJ","Name":"1600 15th (Vara) Unit 325","Units_Available":1,"Building_Name":"Vara","Building_Street_Address":"1600 15th Street","Building_City":"San Francisco","Building_State":"CA","Building_Zip_Code":"94103","LastModifiedDate":"2018-02-21T15:51:46.000+0000","Application_Due_Date":"2017-07-13T00:00:00.000+0000","Building_URL":"http://sfmohcd.org/sites/default/files/Documents/MOH/Housing%20Listing%20Photos/Vara1600-15thSt.jpg","Lottery_Results_Date":"2017-08-04","Lottery_Date":"2017-08-03T20:30:00.000+0000","Lottery_Results":true,"Accepting_Online_Applications":true,"Building_Selection_Criteria":"http://www.caritasmgmtcorp.com/housingopps.html","Reserved_community_minimum_age":0,"hasWaitlist":false,"Id":"a0W0P00000BxjZpUAJ","imageURL":"http://sfmohcd.org/sites/default/files/Documents/MOH/Housing%20Listing%20Photos/Vara1600-15thSt.jpg"},{"unitSummaries":{"reserved":null,"general":[{"unitType":"1 BR","totalUnits":1,"priorities":null,"minSquareFt":750,"minRentalMinIncome":3035.0,"minPercentIncome":null,"minOccupancy":1,"minMonthlyRent":1214.0,"maxSquareFt":750,"maxRentalMinIncome":3035.0,"maxPercentIncome":null,"maxOccupancy":3,"maxMonthlyRent":1214.0,"listingID":"a0W0P00000BxjJxUAJ"}]},"reservedDescriptor":null,"prioritiesDescriptor":null,"listingID":"a0W0P00000BxjJxUAJ","Name":"55 Ninth (AVA) Unit 318","Units_Available":1,"Building_Name":"AVA 55 Ninth","Building_Street_Address":"55 9th Street","Building_City":"San Francisco","Building_State":"CA","Building_Zip_Code":"94103","LastModifiedDate":"2018-02-21T15:51:43.000+0000","Application_Due_Date":"2017-07-12T00:00:00.000+0000","Building_URL":"http://sfmohcd.org/sites/default/files/Documents/MOH/Housing%20Listing%20Photos/AVA55-9thSt.jpg","Lottery_Results_Date":"2017-07-31","Lottery_Date":"2017-07-28T18:00:00.000+0000","Lottery_Results":true,"Accepting_Online_Applications":true,"Building_Selection_Criteria":"https://www.avaloncommunities.com/california/san-francisco-apartments/ava-55-ninth","Reserved_community_minimum_age":0,"hasWaitlist":false,"Id":"a0W0P00000BxjJxUAJ","imageURL":"http://sfmohcd.org/sites/default/files/Documents/MOH/Housing%20Listing%20Photos/AVA55-9thSt.jpg"},{"unitSummaries":{"reserved":null,"general":[{"unitType":"Studio","totalUnits":2,"priorities":null,"minSquareFt":455,"minRentalMinIncome":1610.0,"minPercentIncome":null,"minOccupancy":1,"minMonthlyRent":644.0,"maxSquareFt":455,"maxRentalMinIncome":1610.0,"maxPercentIncome":null,"maxOccupancy":2,"maxMonthlyRent":644.0,"listingID":"a0W0P00000Bxh3dUAB"}]},"reservedDescriptor":null,"prioritiesDescriptor":null,"listingID":"a0W0P00000Bxh3dUAB","Name":"333 Harrison (Rincon Green) Units 249, 349","Units_Available":2,"Building_Name":"Rincon Green Apartments","Building_Street_Address":"333 Harrison Street","Building_City":"San Francisco","Building_State":"CA","Building_Zip_Code":"94105","LastModifiedDate":"2018-02-21T15:51:38.000+0000","Application_Due_Date":"2017-07-01T00:00:00.000+0000","Building_URL":"http://sfmohcd.org/sites/default/files/Images/333HarrisonRinconGreenApts.jpg","Lottery_Results_Date":"2017-07-26","Lottery_Date":"2017-07-25T22:00:00.000+0000","Lottery_Results":true,"Accepting_Online_Applications":true,"Reserved_community_minimum_age":0,"hasWaitlist":false,"Id":"a0W0P00000Bxh3dUAB","imageURL":"http://sfmohcd.org/sites/default/files/Images/333HarrisonRinconGreenApts.jpg"},{"unitSummaries":{"reserved":null,"general":[{"unitType":"2 BR","totalUnits":1,"priorities":null,"minSquareFt":1273,"minRentalMinIncome":5004.0,"minPercentIncome":null,"minOccupancy":2,"minMonthlyRent":2502.0,"maxSquareFt":1273,"maxRentalMinIncome":5004.0,"maxPercentIncome":null,"maxOccupancy":5,"maxMonthlyRent":2502.0,"listingID":"a0W0P00000BxVikUAF"}]},"reservedDescriptor":null,"prioritiesDescriptor":null,"listingID":"a0W0P00000BxVikUAF","Name":"1353-1357 Folsom","Units_Available":1,"Building_Name":"1353-1357 Folsom","Building_Street_Address":"1353-1357 Folsom Street","Building_City":"San Francisco","Building_State":"CA","Building_Zip_Code":"94103","LastModifiedDate":"2018-02-21T15:51:21.000+0000","Application_Due_Date":"2017-06-01T00:00:00.000+0000","Building_URL":"http://sfmohcd.org/sites/default/files/Documents/MOH/Housing%20Listing%20Photos/1353-1357%20Photo.jpg","Lottery_Results_Date":"2017-06-16","Lottery_Date":"2017-06-15T20:00:00.000+0000","Lottery_Results":true,"Accepting_Online_Applications":true,"Building_Selection_Criteria":"http://sfclt.org/Folsom_Street_Building_Criteria_","Reserved_community_minimum_age":0,"hasWaitlist":false,"Id":"a0W0P00000BxVikUAF","imageURL":"http://sfmohcd.org/sites/default/files/Documents/MOH/Housing%20Listing%20Photos/1353-1357%20Photo.jpg"},{"unitSummaries":{"reserved":null,"general":[{"unitType":"1 BR","totalUnits":10,"priorities":null,"minSquareFt":626,"minRentalMinIncome":1938.0,"minPercentIncome":null,"minOccupancy":1,"minMonthlyRent":969.0,"maxSquareFt":626,"maxRentalMinIncome":1938.0,"maxPercentIncome":null,"maxOccupancy":3,"maxMonthlyRent":969.0,"listingID":"a0W0P00000Bxh8oUAB"},{"unitType":"3 BR","totalUnits":7,"priorities":null,"minSquareFt":1105,"minRentalMinIncome":2336.0,"minPercentIncome":null,"minOccupancy":3,"minMonthlyRent":1168.0,"maxSquareFt":1105,"maxRentalMinIncome":2336.0,"maxPercentIncome":null,"maxOccupancy":7,"maxMonthlyRent":1168.0,"listingID":"a0W0P00000Bxh8oUAB"}]},"reservedDescriptor":null,"prioritiesDescriptor":[{"shortDescription":null,"numberOfUnits":2,"name":"Mobility impaired","listingId":"a0W0P00000Bxh8oUAB"}],"listingID":"a0W0P00000Bxh8oUAB","Name":"901 Fairfax (Hunters View - Phase 2B)","Units_Available":0,"Building_Name":"Hunters View Phase 2B","Building_Street_Address":"901 Fairfax Avenue","Building_City":"San Francisco","Building_State":"CA","Building_Zip_Code":"94124","LastModifiedDate":"2018-02-21T15:51:41.000+0000","Application_Due_Date":"2017-05-26T00:00:00.000+0000","Building_URL":"http://sfmohcd.org/sites/default/files/Documents/MOH/Housing%20Listing%20Photos/Capture.JPG","Lottery_Results_Date":"2017-06-23","Lottery_Date":"2017-06-21T17:00:00.000+0000","Lottery_Results":false,"Accepting_Online_Applications":false,"Reserved_community_minimum_age":0,"hasWaitlist":true,"Id":"a0W0P00000Bxh8oUAB","imageURL":"http://sfmohcd.org/sites/default/files/Documents/MOH/Housing%20Listing%20Photos/Capture.JPG"},{"unitSummaries":{"reserved":null,"general":[{"unitType":"Studio","totalUnits":11,"priorities":null,"minSquareFt":510,"minRentalMinIncome":2279.2,"minPercentIncome":null,"minOccupancy":1,"minMonthlyRent":1036.0,"maxSquareFt":668,"maxRentalMinIncome":2279.2,"maxPercentIncome":null,"maxOccupancy":2,"maxMonthlyRent":1036.0,"listingID":"a0W0P00000DZfSpUAL"},{"unitType":"1 BR","totalUnits":21,"priorities":null,"minSquareFt":631,"minRentalMinIncome":2607.0,"minPercentIncome":null,"minOccupancy":1,"minMonthlyRent":1185.0,"maxSquareFt":654,"maxRentalMinIncome":2607.0,"maxPercentIncome":null,"maxOccupancy":3,"maxMonthlyRent":1185.0,"listingID":"a0W0P00000DZfSpUAL"},{"unitType":"2 BR","totalUnits":22,"priorities":null,"minSquareFt":1010,"minRentalMinIncome":2932.6,"minPercentIncome":null,"minOccupancy":2,"minMonthlyRent":1333.0,"maxSquareFt":1053,"maxRentalMinIncome":2932.6,"maxPercentIncome":null,"maxOccupancy":5,"maxMonthlyRent":1333.0,"listingID":"a0W0P00000DZfSpUAL"},{"unitType":"3 BR","totalUnits":1,"priorities":null,"minSquareFt":1312,"minRentalMinIncome":3258.2,"minPercentIncome":null,"minOccupancy":3,"minMonthlyRent":1481.0,"maxSquareFt":1312,"maxRentalMinIncome":3258.2,"maxPercentIncome":null,"maxOccupancy":7,"maxMonthlyRent":1481.0,"listingID":"a0W0P00000DZfSpUAL"}]},"reservedDescriptor":null,"prioritiesDescriptor":null,"listingID":"a0W0P00000DZfSpUAL","Name":"855 Brannan","Units_Available":55,"Building_Name":"855 Brannan","Building_Street_Address":"855 Brannan Street","Building_City":"San Francisco","Building_State":"CA","Building_Zip_Code":"94103","LastModifiedDate":"2018-02-21T15:53:35.000+0000","Application_Due_Date":"2017-05-18T00:00:00.000+0000","Building_URL":"http://sfmohcd.org/sites/default/files/855%20Brannan.png","Lottery_Results_Date":"2017-06-07","Lottery_Date":"2017-06-07T17:00:00.000+0000","Lottery_Results":true,"Accepting_Online_Applications":true,"Reserved_community_minimum_age":0,"hasWaitlist":false,"Id":"a0W0P00000DZfSpUAL","imageURL":"http://sfmohcd.org/sites/default/files/855%20Brannan.png"},{"unitSummaries":{"reserved":null,"general":[{"unitType":"Studio","totalUnits":1,"priorities":null,"minSquareFt":568,"minRentalMinIncome":2220.0,"minPercentIncome":null,"minOccupancy":1,"minMonthlyRent":1110.0,"maxSquareFt":568,"maxRentalMinIncome":2220.0,"maxPercentIncome":null,"maxOccupancy":2,"maxMonthlyRent":1110.0,"listingID":"a0W0P00000BxRSLUA3"}]},"reservedDescriptor":null,"prioritiesDescriptor":null,"listingID":"a0W0P00000BxRSLUA3","Name":"900 Folsom (Mosso) Unit 742","Units_Available":1,"Building_Name":"Mosso","Building_Street_Address":"900 Folsom Street","Building_City":"San Francisco","Building_State":"CA","Building_Zip_Code":"94107","LastModifiedDate":"2018-02-21T15:51:19.000+0000","Application_Due_Date":"2017-05-12T00:00:00.000+0000","Building_URL":"http://cdn.c.photoshelter.com/img-get2/I0000FeFdkZv7360/sec=wd0sd0oe0lwe0ms1000ed20170310tgHKBgiDA0gleZD/fill=1020x683/PS-002-Mosso.jpg","Lottery_Results_Date":"2017-05-26","Lottery_Date":"2017-05-25T18:30:00.000+0000","Lottery_Results":true,"Accepting_Online_Applications":true,"Building_Selection_Criteria":"http://www.essexapartmenthomes.com/mosso-affordable-housing","Reserved_community_minimum_age":0,"hasWaitlist":false,"Id":"a0W0P00000BxRSLUA3","imageURL":"http://cdn.c.photoshelter.com/img-get2/I0000FeFdkZv7360/sec=wd0sd0oe0lwe0ms1000ed20170310tgHKBgiDA0gleZD/fill=1020x683/PS-002-Mosso.jpg"},{"unitSummaries":{"reserved":null,"general":[{"unitType":"1 BR","totalUnits":1,"priorities":null,"minSquareFt":597,"minRentalMinIncome":3172.5,"minPercentIncome":null,"minOccupancy":1,"minMonthlyRent":1269.0,"maxSquareFt":597,"maxRentalMinIncome":3172.5,"maxPercentIncome":null,"maxOccupancy":3,"maxMonthlyRent":1269.0,"listingID":"a0W0P00000DROL7UAP"}]},"reservedDescriptor":null,"prioritiesDescriptor":null,"listingID":"a0W0P00000DROL7UAP","Name":"1010 16th (Potrero 1010) Unit 236","Units_Available":1,"Building_Name":"Potrero 1010","Building_Street_Address":"1010 16th Street","Building_City":"San Francisco","Building_State":"CA","Building_Zip_Code":"94141","LastModifiedDate":"2018-02-23T19:45:21.000+0000","Application_Due_Date":"2017-05-05T00:00:00.000+0000","Building_URL":"http://sfmohcd.org/sites/default/files/Documents/MOH/Housing%20Listing%20Photos/Potrero1010-16thSt.jpg","Lottery_Results_Date":"2017-05-23","Lottery_Date":"2017-05-22T17:30:00.000+0000","Lottery_Results":true,"Accepting_Online_Applications":true,"Building_Selection_Criteria":"https://sites.google.com/site/potrero1010bmr2015/income-rent-limits","Reserved_community_minimum_age":0,"hasWaitlist":false,"Id":"a0W0P00000DROL7UAP","imageURL":"http://sfmohcd.org/sites/default/files/Documents/MOH/Housing%20Listing%20Photos/Potrero1010-16thSt.jpg"},{"unitSummaries":{"reserved":null,"general":[{"unitType":"1 BR","totalUnits":6,"priorities":null,"minSquareFt":543,"minRentalMinIncome":2266.0,"minPercentIncome":null,"minOccupancy":1,"minMonthlyRent":1133.0,"maxSquareFt":587,"maxRentalMinIncome":2266.0,"maxPercentIncome":null,"maxOccupancy":3,"maxMonthlyRent":1133.0,"listingID":"a0W0P00000DZch1UAD"},{"unitType":"2 BR","totalUnits":4,"priorities":null,"minSquareFt":710,"minRentalMinIncome":2528.0,"minPercentIncome":null,"minOccupancy":2,"minMonthlyRent":1264.0,"maxSquareFt":884,"maxRentalMinIncome":2528.0,"maxPercentIncome":null,"maxOccupancy":5,"maxMonthlyRent":1264.0,"listingID":"a0W0P00000DZch1UAD"}]},"reservedDescriptor":null,"prioritiesDescriptor":null,"listingID":"a0W0P00000DZch1UAD","Name":"181 Sanchez (Duboce)","Units_Available":10,"Building_Name":"Duboce","Building_Street_Address":"181 Sanchez Street","Building_City":"San Francisco","Building_State":"CA","Building_Zip_Code":"94114","LastModifiedDate":"2018-02-23T22:00:51.000+0000","Application_Due_Date":"2017-05-03T00:00:00.000+0000","Building_URL":"http://sfmohcd.org/sites/default/files/Duboce.png","Lottery_Results_Date":"2017-05-31","Lottery_Date":"2017-05-24T20:30:00.000+0000","Lottery_Results":true,"Accepting_Online_Applications":true,"Reserved_community_minimum_age":0,"hasWaitlist":false,"Id":"a0W0P00000DZch1UAD","imageURL":"http://sfmohcd.org/sites/default/files/Duboce.png"},{"unitSummaries":{"reserved":null,"general":[{"unitType":"Studio","totalUnits":3,"priorities":null,"minSquareFt":382,"minRentalMinIncome":1982.0,"minPercentIncome":null,"minOccupancy":1,"minMonthlyRent":991.0,"maxSquareFt":382,"maxRentalMinIncome":1982.0,"maxPercentIncome":null,"maxOccupancy":2,"maxMonthlyRent":991.0,"listingID":"a0W0P00000DZcSuUAL"},{"unitType":"1 BR","totalUnits":66,"priorities":null,"minSquareFt":561,"minRentalMinIncome":2266.0,"minPercentIncome":null,"minOccupancy":1,"minMonthlyRent":1133.0,"maxSquareFt":648,"maxRentalMinIncome":2266.0,"maxPercentIncome":null,"maxOccupancy":3,"maxMonthlyRent":1133.0,"listingID":"a0W0P00000DZcSuUAL"},{"unitType":"2 BR","totalUnits":13,"priorities":null,"minSquareFt":685,"minRentalMinIncome":2528.0,"minPercentIncome":null,"minOccupancy":2,"minMonthlyRent":1264.0,"maxSquareFt":758,"maxRentalMinIncome":2528.0,"maxPercentIncome":null,"maxOccupancy":5,"maxMonthlyRent":1264.0,"listingID":"a0W0P00000DZcSuUAL"}]},"reservedDescriptor":null,"prioritiesDescriptor":null,"listingID":"a0W0P00000DZcSuUAL","Name":"33 Eighth (Trinity Phase 3)","Units_Available":0,"Building_Name":"Trinity Place Phase 3","Building_Street_Address":"33 8th Street","Building_City":"San Francisco","Building_State":"CA","Building_Zip_Code":"94103","LastModifiedDate":"2018-02-27T13:52:24.000+0000","Application_Due_Date":"2017-05-02T00:00:00.000+0000","Building_URL":"http://sfmohcd.org/sites/default/files/Trinity%20Phase%203.png","Lottery_Results_Date":"2017-05-30","Lottery_Date":"2017-05-23T19:00:00.000+0000","Lottery_Results":true,"Accepting_Online_Applications":true,"Reserved_community_minimum_age":0,"hasWaitlist":false,"Id":"a0W0P00000DZcSuUAL","imageURL":"http://sfmohcd.org/sites/default/files/Trinity%20Phase%203.png"},{"unitSummaries":{"reserved":null,"general":[{"unitType":"Studio","totalUnits":24,"priorities":null,"minSquareFt":270,"minRentalMinIncome":1814.0,"minPercentIncome":null,"minOccupancy":1,"minMonthlyRent":907.0,"maxSquareFt":415,"maxRentalMinIncome":2190.0,"maxPercentIncome":null,"maxOccupancy":2,"maxMonthlyRent":1095.0,"listingID":"a0W0P00000DZagkUAD"}]},"reservedDescriptor":null,"prioritiesDescriptor":[{"shortDescription":null,"numberOfUnits":3,"name":"Mobility impaired","listingId":"a0W0P00000DZagkUAD"},{"shortDescription":null,"numberOfUnits":1,"name":"Hearing impaired","listingId":"a0W0P00000DZagkUAD"}],"listingID":"a0W0P00000DZagkUAD","Name":"800 Presidio (JBA/YHC at Booker T. Washington)","Units_Available":24,"Building_Name":"Burton Advocates for Youth at Booker T. Washington","Building_Street_Address":"800 Presidio Avenue","Building_City":"San Francisco","Building_State":"CA","Building_Zip_Code":"94115","LastModifiedDate":"2018-02-21T15:53:17.000+0000","Application_Due_Date":"2017-04-28T00:00:00.000+0000","Building_URL":"http://sfmohcd.org/sites/default/files/Documents/MOH/Housing%20Listing%20Photos/Booker%20T.%20Washington_0.png","Lottery_Results_Date":"2017-05-26","Lottery_Date":"2017-05-19T17:00:00.000+0000","Lottery_Results":true,"Accepting_Online_Applications":false,"Reserved_community_minimum_age":0,"hasWaitlist":true,"Id":"a0W0P00000DZagkUAD","imageURL":"http://sfmohcd.org/sites/default/files/Documents/MOH/Housing%20Listing%20Photos/Booker%20T.%20Washington_0.png"},{"unitSummaries":{"reserved":null,"general":[{"unitType":"1 BR","totalUnits":10,"priorities":null,"minSquareFt":572,"minRentalMinIncome":2266.0,"minPercentIncome":null,"minOccupancy":1,"minMonthlyRent":1133.0,"maxSquareFt":722,"maxRentalMinIncome":2266.0,"maxPercentIncome":null,"maxOccupancy":3,"maxMonthlyRent":1133.0,"listingID":"a0W0P00000DZabeUAD"},{"unitType":"2 BR","totalUnits":10,"priorities":null,"minSquareFt":790,"minRentalMinIncome":2528.0,"minPercentIncome":null,"minOccupancy":2,"minMonthlyRent":1264.0,"maxSquareFt":1038,"maxRentalMinIncome":2528.0,"maxPercentIncome":null,"maxOccupancy":5,"maxMonthlyRent":1264.0,"listingID":"a0W0P00000DZabeUAD"}]},"reservedDescriptor":null,"prioritiesDescriptor":null,"listingID":"a0W0P00000DZabeUAD","Name":"5880 Third (Waterbend)","Units_Available":20,"Building_Name":"Waterbend","Building_Street_Address":"5880 Third Street","Building_City":"San Francisco","Building_State":"CA","Building_Zip_Code":"94124","LastModifiedDate":"2018-02-21T15:53:15.000+0000","Application_Due_Date":"2017-04-26T00:00:00.000+0000","Building_URL":"http://sfmohcd.org/sites/default/files/Documents/MOH/Housing%20Listing%20Photos/wb.jpg","Lottery_Results_Date":"2017-05-17","Lottery_Date":"2017-05-17T20:30:00.000+0000","Lottery_Results":true,"Accepting_Online_Applications":false,"Reserved_community_minimum_age":0,"hasWaitlist":false,"Id":"a0W0P00000DZabeUAD","imageURL":"http://sfmohcd.org/sites/default/files/Documents/MOH/Housing%20Listing%20Photos/wb.jpg"},{"unitSummaries":{"reserved":null,"general":[{"unitType":"SRO","totalUnits":100,"priorities":null,"minSquareFt":126,"minRentalMinIncome":1356.0,"minPercentIncome":null,"minOccupancy":1,"minMonthlyRent":678.0,"maxSquareFt":268,"maxRentalMinIncome":1414.0,"maxPercentIncome":null,"maxOccupancy":1,"maxMonthlyRent":707.0,"listingID":"a0W0P00000DZalnUAD"}]},"reservedDescriptor":null,"prioritiesDescriptor":[{"shortDescription":null,"numberOfUnits":13,"name":"Mobility impaired","listingId":"a0W0P00000DZalnUAD"},{"shortDescription":null,"numberOfUnits":2,"name":"Hearing/Vision impaired","listingId":"a0W0P00000DZalnUAD"}],"listingID":"a0W0P00000DZalnUAD","Name":"34 Turk (Dalt Hotel)","Units_Available":0,"Building_Name":"Dalt Hotel","Building_Street_Address":"34 Turk Street","Building_City":"San Francisco","Building_State":"CA","Building_Zip_Code":"94102","LastModifiedDate":"2018-02-21T15:53:20.000+0000","Application_Due_Date":"2017-04-15T00:00:00.000+0000","Building_URL":"http://sfmohcd.org/sites/default/files/Documents/MOH/Housing%20Listing%20Photos/Dalt%20Hotel.jpg","Lottery_Results_Date":"2017-05-12","Lottery_Date":"2017-05-05T17:30:00.000+0000","Lottery_Results":true,"Accepting_Online_Applications":false,"Reserved_community_minimum_age":0,"hasWaitlist":true,"Id":"a0W0P00000DZalnUAD","imageURL":"http://sfmohcd.org/sites/default/files/Documents/MOH/Housing%20Listing%20Photos/Dalt%20Hotel.jpg"},{"unitSummaries":{"reserved":null,"general":[{"unitType":"SRO","totalUnits":89,"priorities":null,"minSquareFt":null,"minRentalMinIncome":1414.0,"minPercentIncome":null,"minOccupancy":1,"minMonthlyRent":707.0,"maxSquareFt":null,"maxRentalMinIncome":1414.0,"maxPercentIncome":null,"maxOccupancy":1,"maxMonthlyRent":707.0,"listingID":"a0W0P00000DZamCUAT"}]},"reservedDescriptor":null,"prioritiesDescriptor":[{"shortDescription":null,"numberOfUnits":12,"name":"Mobility impaired","listingId":"a0W0P00000DZamCUAT"},{"shortDescription":null,"numberOfUnits":4,"name":"Hearing/Vision impaired","listingId":"a0W0P00000DZamCUAT"}],"listingID":"a0W0P00000DZamCUAT","Name":"44 McAllister (Civic Center Residence)","Units_Available":0,"Building_Name":"Civic Center Residence","Building_Street_Address":"44 McAllister Street","Building_City":"San Francisco","Building_State":"CA","Building_Zip_Code":"94102","LastModifiedDate":"2018-02-21T15:53:24.000+0000","Application_Due_Date":"2017-04-15T00:00:00.000+0000","Building_URL":"http://sfmohcd.org/sites/default/files/Documents/MOH/Housing%20Listing%20Photos/44-McAllister-Civic-Center-Residence.jpg","Lottery_Results_Date":"2017-05-05","Lottery_Date":"2017-04-28T17:30:00.000+0000","Lottery_Results":true,"Accepting_Online_Applications":false,"Reserved_community_minimum_age":0,"hasWaitlist":true,"Id":"a0W0P00000DZamCUAT","imageURL":"http://sfmohcd.org/sites/default/files/Documents/MOH/Housing%20Listing%20Photos/44-McAllister-Civic-Center-Residence.jpg"},{"unitSummaries":{"reserved":null,"general":[{"unitType":"2 BR","totalUnits":1,"priorities":null,"minSquareFt":950,"minRentalMinIncome":4675.0,"minPercentIncome":null,"minOccupancy":2,"minMonthlyRent":1870.0,"maxSquareFt":950,"maxRentalMinIncome":4675.0,"maxPercentIncome":null,"maxOccupancy":5,"maxMonthlyRent":1870.0,"listingID":"a0W0P00000DZY0JUAX"}]},"reservedDescriptor":null,"prioritiesDescriptor":null,"listingID":"a0W0P00000DZY0JUAX","Name":"1 Polk (Argenta) Unit 403","Units_Available":1,"Building_Name":"Argenta","Building_Street_Address":"1 Polk Street","Building_City":"San Francisco","Building_State":"CA","Building_Zip_Code":"94102","LastModifiedDate":"2018-02-23T19:12:49.000+0000","Application_Due_Date":"2017-03-22T00:00:00.000+0000","Building_URL":"http://medialibrarycdn.entrata.com/media_library/2014/53988d517c7f9751.jpg","Lottery_Results_Date":"2017-04-05","Lottery_Date":"2017-04-04T18:00:00.000+0000","Lottery_Results":true,"Accepting_Online_Applications":true,"Building_Selection_Criteria":"http://www.caritasmgmtcorp.com/housingopps.html","Reserved_community_minimum_age":0,"hasWaitlist":false,"Id":"a0W0P00000DZY0JUAX","imageURL":"http://medialibrarycdn.entrata.com/media_library/2014/53988d517c7f9751.jpg"},{"unitSummaries":{"reserved":null,"general":[{"unitType":"Studio","totalUnits":12,"priorities":null,"minSquareFt":457,"minRentalMinIncome":2477.5,"minPercentIncome":null,"minOccupancy":1,"minMonthlyRent":991.0,"maxSquareFt":547,"maxRentalMinIncome":2477.5,"maxPercentIncome":null,"maxOccupancy":2,"maxMonthlyRent":991.0,"listingID":"a0W0P00000DZKPdUAP"},{"unitType":"1 BR","totalUnits":6,"priorities":null,"minSquareFt":592,"minRentalMinIncome":2832.5,"minPercentIncome":null,"minOccupancy":1,"minMonthlyRent":1133.0,"maxSquareFt":629,"maxRentalMinIncome":2832.5,"maxPercentIncome":null,"maxOccupancy":3,"maxMonthlyRent":1133.0,"listingID":"a0W0P00000DZKPdUAP"},{"unitType":"2 BR","totalUnits":15,"priorities":null,"minSquareFt":461,"minRentalMinIncome":2477.5,"minPercentIncome":null,"minOccupancy":2,"minMonthlyRent":991.0,"maxSquareFt":1228,"maxRentalMinIncome":3160.0,"maxPercentIncome":null,"maxOccupancy":5,"maxMonthlyRent":1264.0,"listingID":"a0W0P00000DZKPdUAP"},{"unitType":"3 BR","totalUnits":1,"priorities":null,"minSquareFt":1222,"minRentalMinIncome":3477.5,"minPercentIncome":null,"minOccupancy":3,"minMonthlyRent":1391.0,"maxSquareFt":1222,"maxRentalMinIncome":3477.5,"maxPercentIncome":null,"maxOccupancy":7,"maxMonthlyRent":1391.0,"listingID":"a0W0P00000DZKPdUAP"}]},"reservedDescriptor":null,"prioritiesDescriptor":null,"listingID":"a0W0P00000DZKPdUAP","Name":"2660 Third (Abaca)","Units_Available":34,"Building_Name":"Abaca","Building_Street_Address":"2660 3rd Street","Building_City":"San Francisco","Building_State":"CA","Building_Zip_Code":"94107","LastModifiedDate":"2018-02-21T15:52:57.000+0000","Application_Due_Date":"2017-03-10T01:00:00.000+0000","Building_URL":"http://www.abacasf.com/dmslivecafe/3/529784/16_0708_OA_Abaca_SplashPage_Rendering_2_new.jpg?quality=85&","Lottery_Results_Date":"2017-04-07","Lottery_Date":"2017-03-31T20:00:00.000+0000","Lottery_Results":true,"Accepting_Online_Applications":false,"Reserved_community_minimum_age":0,"hasWaitlist":false,"Id":"a0W0P00000DZKPdUAP","imageURL":"http://www.abacasf.com/dmslivecafe/3/529784/16_0708_OA_Abaca_SplashPage_Rendering_2_new.jpg?quality=85&"},{"unitSummaries":{"reserved":null,"general":[{"unitType":"1 BR","totalUnits":1,"priorities":null,"minSquareFt":471,"minRentalMinIncome":2266.0,"minPercentIncome":null,"minOccupancy":1,"minMonthlyRent":1133.0,"maxSquareFt":471,"maxRentalMinIncome":2266.0,"maxPercentIncome":null,"maxOccupancy":3,"maxMonthlyRent":1133.0,"listingID":"a0W0P00000DZOfbUAH"}]},"reservedDescriptor":null,"prioritiesDescriptor":null,"listingID":"a0W0P00000DZOfbUAH","Name":"2121 Third (The Gantry) Unit 209","Units_Available":1,"Building_Name":"The Gantry","Building_Street_Address":"2121 Third Street","Building_City":"San Francisco","Building_State":"CA","Building_Zip_Code":"94107","LastModifiedDate":"2018-02-21T15:53:00.000+0000","Application_Due_Date":"2017-02-24T01:00:00.000+0000","Building_URL":"http://www.socketsite.com/wp-content/uploads/2011/09/2121-3rd-Street-Rendering.jpg","Lottery_Results_Date":"2017-03-14","Lottery_Date":"2017-03-10T21:00:00.000+0000","Lottery_Results":true,"Accepting_Online_Applications":false,"Building_Selection_Criteria":"http://www.thegantryapts.com","Reserved_community_minimum_age":0,"hasWaitlist":false,"Id":"a0W0P00000DZOfbUAH","imageURL":"http://www.socketsite.com/wp-content/uploads/2011/09/2121-3rd-Street-Rendering.jpg"},{"unitSummaries":{"reserved":null,"general":[{"unitType":"1 BR","totalUnits":14,"priorities":null,"minSquareFt":670,"minRentalMinIncome":3774.0,"minPercentIncome":null,"minOccupancy":1,"minMonthlyRent":1887.0,"maxSquareFt":691,"maxRentalMinIncome":3774.0,"maxPercentIncome":null,"maxOccupancy":3,"maxMonthlyRent":1887.0,"listingID":"a0W0P00000DZCJhUAP"},{"unitType":"2 BR","totalUnits":11,"priorities":null,"minSquareFt":994,"minRentalMinIncome":4224.0,"minPercentIncome":null,"minOccupancy":2,"minMonthlyRent":2112.0,"maxSquareFt":1018,"maxRentalMinIncome":4224.0,"maxPercentIncome":null,"maxOccupancy":5,"maxMonthlyRent":2112.0,"listingID":"a0W0P00000DZCJhUAP"},{"unitType":"3 BR","totalUnits":1,"priorities":null,"minSquareFt":1420,"minRentalMinIncome":4668.0,"minPercentIncome":null,"minOccupancy":3,"minMonthlyRent":2334.0,"maxSquareFt":1420,"maxRentalMinIncome":4668.0,"maxPercentIncome":null,"maxOccupancy":7,"maxMonthlyRent":2334.0,"listingID":"a0W0P00000DZCJhUAP"}]},"reservedDescriptor":null,"prioritiesDescriptor":null,"listingID":"a0W0P00000DZCJhUAP","Name":"360 Berry (EVIVA)","Units_Available":26,"Building_Name":"EVIVA","Building_Street_Address":"360 Berry Street","Building_City":"San Francisco","Building_State":"CA","Building_Zip_Code":"94158","LastModifiedDate":"2018-02-21T15:52:42.000+0000","Application_Due_Date":"2017-02-11T01:00:00.000+0000","Building_URL":"http://image1.apartmentfinder.com/i2/K1Y30DQIZmWFLuejFPXlhIEzGQRx7_QeJyP-FmSy3OI/110/eviva-mission-bay-san-francisco-ca-primary-photo.jpg","Lottery_Results_Date":"2017-03-15","Lottery_Date":"2017-03-08T21:00:00.000+0000","Lottery_Results":true,"Accepting_Online_Applications":false,"Reserved_community_minimum_age":0,"hasWaitlist":false,"Id":"a0W0P00000DZCJhUAP","imageURL":"http://image1.apartmentfinder.com/i2/K1Y30DQIZmWFLuejFPXlhIEzGQRx7_QeJyP-FmSy3OI/110/eviva-mission-bay-san-francisco-ca-primary-photo.jpg"},{"unitSummaries":{"reserved":null,"general":[{"unitType":"Studio","totalUnits":6,"priorities":null,"minSquareFt":332,"minRentalMinIncome":2477.5,"minPercentIncome":null,"minOccupancy":1,"minMonthlyRent":991.0,"maxSquareFt":415,"maxRentalMinIncome":2477.5,"maxPercentIncome":null,"maxOccupancy":2,"maxMonthlyRent":991.0,"listingID":"a0W0P00000DZ8aFUAT"},{"unitType":"1 BR","totalUnits":4,"priorities":null,"minSquareFt":531,"minRentalMinIncome":2832.5,"minPercentIncome":null,"minOccupancy":1,"minMonthlyRent":1133.0,"maxSquareFt":646,"maxRentalMinIncome":2832.5,"maxPercentIncome":null,"maxOccupancy":3,"maxMonthlyRent":1133.0,"listingID":"a0W0P00000DZ8aFUAT"},{"unitType":"2 BR","totalUnits":6,"priorities":null,"minSquareFt":828,"minRentalMinIncome":3160.0,"minPercentIncome":null,"minOccupancy":2,"minMonthlyRent":1264.0,"maxSquareFt":889,"maxRentalMinIncome":3160.0,"maxPercentIncome":null,"maxOccupancy":5,"maxMonthlyRent":1264.0,"listingID":"a0W0P00000DZ8aFUAT"},{"unitType":"3 BR","totalUnits":1,"priorities":null,"minSquareFt":1045,"minRentalMinIncome":3477.5,"minPercentIncome":null,"minOccupancy":3,"minMonthlyRent":1391.0,"maxSquareFt":1045,"maxRentalMinIncome":3477.5,"maxPercentIncome":null,"maxOccupancy":7,"maxMonthlyRent":1391.0,"listingID":"a0W0P00000DZ8aFUAT"}]},"reservedDescriptor":null,"prioritiesDescriptor":null,"listingID":"a0W0P00000DZ8aFUAT","Name":"680 Indiana (O&M Apartments)","Units_Available":17,"Building_Name":"O&M Apartments","Building_Street_Address":"680 Indiana Street","Building_City":"San Francisco","Building_State":"CA","Building_Zip_Code":"94107","LastModifiedDate":"2018-02-21T15:52:32.000+0000","Application_Due_Date":"2017-01-21T01:00:00.000+0000","Building_URL":"http://sfmohcd.org/sites/default/files/Documents/MOH/O%26M%20Picture.jpg","Lottery_Results_Date":"2017-02-17","Lottery_Date":"2017-02-10T22:00:00.000+0000","Lottery_Results":true,"Accepting_Online_Applications":false,"Building_Selection_Criteria":"http://oandmsf.com/","Reserved_community_minimum_age":0,"hasWaitlist":false,"Id":"a0W0P00000DZ8aFUAT","imageURL":"http://sfmohcd.org/sites/default/files/Documents/MOH/O%26M%20Picture.jpg"},{"unitSummaries":{"reserved":null,"general":[{"unitType":"Studio","totalUnits":5,"priorities":null,"minSquareFt":445,"minRentalMinIncome":1982.0,"minPercentIncome":null,"minOccupancy":1,"minMonthlyRent":991.0,"maxSquareFt":494,"maxRentalMinIncome":1982.0,"maxPercentIncome":null,"maxOccupancy":2,"maxMonthlyRent":991.0,"listingID":"a0W0P00000DZ4dTUAT"},{"unitType":"1 BR","totalUnits":32,"priorities":null,"minSquareFt":704,"minRentalMinIncome":2266.0,"minPercentIncome":null,"minOccupancy":1,"minMonthlyRent":1133.0,"maxSquareFt":791,"maxRentalMinIncome":2266.0,"maxPercentIncome":null,"maxOccupancy":3,"maxMonthlyRent":1133.0,"listingID":"a0W0P00000DZ4dTUAT"},{"unitType":"2 BR","totalUnits":25,"priorities":null,"minSquareFt":982,"minRentalMinIncome":2528.0,"minPercentIncome":null,"minOccupancy":2,"minMonthlyRent":1264.0,"maxSquareFt":1059,"maxRentalMinIncome":2528.0,"maxPercentIncome":null,"maxOccupancy":5,"maxMonthlyRent":1264.0,"listingID":"a0W0P00000DZ4dTUAT"}]},"reservedDescriptor":null,"prioritiesDescriptor":null,"listingID":"a0W0P00000DZ4dTUAT","Name":"1222 Harrison (L Seven)","Units_Available":62,"Building_Name":"L Seven","Building_Street_Address":"1222 Harrison Street","Building_City":"San Francisco","Building_State":"CA","Building_Zip_Code":"94103","LastModifiedDate":"2018-02-27T05:52:06.000+0000","Application_Due_Date":"2017-01-13T01:00:00.000+0000","Building_URL":"http://sfmohcd.org/sites/default/files/Documents/MOH/Housing%20Listing%20Photos/LSeven-1222HarrisonSt.JPG","Lottery_Results_Date":"2017-02-01","Lottery_Date":"2017-02-01T21:00:00.000+0000","Lottery_Results":true,"Accepting_Online_Applications":true,"Building_Selection_Criteria":"http://sfmohcd.org/sites/default/files/Resident%20Selection%20Criteria/FINAL%20Form%20616%20General%20Rental%20and%20Occupancy%20Criteria%20Guidelines%20%28L%20Seven%20BMR%20O...%2012.9.2016.pdf","Reserved_community_minimum_age":0,"hasWaitlist":false,"Id":"a0W0P00000DZ4dTUAT","imageURL":"http://sfmohcd.org/sites/default/files/Documents/MOH/Housing%20Listing%20Photos/LSeven-1222HarrisonSt.JPG"},{"unitSummaries":{"reserved":null,"general":[{"unitType":"1 BR","totalUnits":1,"priorities":null,"minSquareFt":446,"minRentalMinIncome":2832.5,"minPercentIncome":null,"minOccupancy":1,"minMonthlyRent":1133.0,"maxSquareFt":446,"maxRentalMinIncome":2832.5,"maxPercentIncome":null,"maxOccupancy":3,"maxMonthlyRent":1133.0,"listingID":"a0W0P00000DYlxMUAT"},{"unitType":"2 BR","totalUnits":2,"priorities":null,"minSquareFt":645,"minRentalMinIncome":3160.0,"minPercentIncome":null,"minOccupancy":2,"minMonthlyRent":1264.0,"maxSquareFt":723,"maxRentalMinIncome":3160.0,"maxPercentIncome":null,"maxOccupancy":5,"maxMonthlyRent":1264.0,"listingID":"a0W0P00000DYlxMUAT"}]},"reservedDescriptor":null,"prioritiesDescriptor":null,"listingID":"a0W0P00000DYlxMUAT","Name":"280 Brighton","Units_Available":3,"Building_Name":"280 Brighton","Building_Street_Address":"280 Brighton Avenue","Building_City":"San Francisco","Building_State":"CA","Building_Zip_Code":"94112","LastModifiedDate":"2018-02-26T17:44:03.000+0000","Application_Due_Date":"2016-12-01T01:00:00.000+0000","Building_URL":"https://static.wixstatic.com/media/54498e_49fdaf8d874c4e65975e9e6bd97bca16.png/v1/fill/w_1201,h_774,al_c,usm_0.66_1.00_0.01/54498e_49fdaf8d874c4e65975e9e6bd97bca16.png","Lottery_Results_Date":"2016-12-28","Lottery_Date":"2016-12-21T20:00:00.000+0000","Lottery_Results":true,"Accepting_Online_Applications":true,"Reserved_community_minimum_age":0,"hasWaitlist":false,"Id":"a0W0P00000DYlxMUAT","imageURL":"https://static.wixstatic.com/media/54498e_49fdaf8d874c4e65975e9e6bd97bca16.png/v1/fill/w_1201,h_774,al_c,usm_0.66_1.00_0.01/54498e_49fdaf8d874c4e65975e9e6bd97bca16.png"}]}